{
"meta":{"test_sets":[],"test_metrics":[],"learn_metrics":[{"best_value":"Min","name":"RMSE"}],"launch_mode":"Train","parameters":"","iteration_count":1000,"learn_sets":["learn"],"name":"experiment"},
"iterations":[
{"learn":[14.59871775],"iteration":0,"passed_time":0.1394460299,"remaining_time":139.3065838},
{"learn":[14.22518863],"iteration":1,"passed_time":0.141441643,"remaining_time":70.57937987},
{"learn":[13.8866124],"iteration":2,"passed_time":0.1434353917,"remaining_time":47.66836185},
{"learn":[13.52356875],"iteration":3,"passed_time":0.1456226113,"remaining_time":36.26003022},
{"learn":[13.18870211],"iteration":4,"passed_time":0.1479558215,"remaining_time":29.44320847},
{"learn":[12.9124226],"iteration":5,"passed_time":0.1500651226,"remaining_time":24.86078864},
{"learn":[12.60003351],"iteration":6,"passed_time":0.1522822894,"remaining_time":21.60233048},
{"learn":[12.32990573],"iteration":7,"passed_time":0.1543611701,"remaining_time":19.14078509},
{"learn":[12.0660619],"iteration":8,"passed_time":0.1559999739,"remaining_time":17.17733046},
{"learn":[11.77309809],"iteration":9,"passed_time":0.1576105809,"remaining_time":15.60344751},
{"learn":[11.49227636],"iteration":10,"passed_time":0.1593276205,"remaining_time":14.32500151},
{"learn":[11.26264833],"iteration":11,"passed_time":0.1612176559,"remaining_time":13.27358701},
{"learn":[11.04260393],"iteration":12,"passed_time":0.1629965256,"remaining_time":12.37519775},
{"learn":[10.79916926],"iteration":13,"passed_time":0.1646568811,"remaining_time":11.59654891},
{"learn":[10.5541002],"iteration":14,"passed_time":0.1660066407,"remaining_time":10.90110274},
{"learn":[10.31918115],"iteration":15,"passed_time":0.167202535,"remaining_time":10.2829559},
{"learn":[10.10004441],"iteration":16,"passed_time":0.1683271469,"remaining_time":9.73326973},
{"learn":[9.894556723],"iteration":17,"passed_time":0.1693104208,"remaining_time":9.236824067},
{"learn":[9.690174082],"iteration":18,"passed_time":0.1701883064,"remaining_time":8.787090975},
{"learn":[9.506034866],"iteration":19,"passed_time":0.171102528,"remaining_time":8.38402387},
{"learn":[9.338524633],"iteration":20,"passed_time":0.172330734,"remaining_time":8.033894693},
{"learn":[9.170203312],"iteration":21,"passed_time":0.1734728029,"remaining_time":7.711654601},
{"learn":[9.010299969],"iteration":22,"passed_time":0.1743862875,"remaining_time":7.407626211},
{"learn":[8.843866678],"iteration":23,"passed_time":0.1751028418,"remaining_time":7.120848901},
{"learn":[8.690548059],"iteration":24,"passed_time":0.176107262,"remaining_time":6.868183218},
{"learn":[8.555307687],"iteration":25,"passed_time":0.1769203967,"remaining_time":6.627710246},
{"learn":[8.413851302],"iteration":26,"passed_time":0.1776237991,"remaining_time":6.401035428},
{"learn":[8.29256019],"iteration":27,"passed_time":0.1791086549,"remaining_time":6.217629019},
{"learn":[8.162193833],"iteration":28,"passed_time":0.1799304536,"remaining_time":6.024567945},
{"learn":[8.040736294],"iteration":29,"passed_time":0.1806189996,"remaining_time":5.840014322},
{"learn":[7.921220278],"iteration":30,"passed_time":0.1814060923,"remaining_time":5.670403337},
{"learn":[7.809589039],"iteration":31,"passed_time":0.1821281479,"remaining_time":5.509376474},
{"learn":[7.699675801],"iteration":32,"passed_time":0.1828099499,"remaining_time":5.356885501},
{"learn":[7.60645267],"iteration":33,"passed_time":0.1835401367,"remaining_time":5.214699179},
{"learn":[7.498880302],"iteration":34,"passed_time":0.1842350344,"remaining_time":5.079623091},
{"learn":[7.401158744],"iteration":35,"passed_time":0.1850192757,"remaining_time":4.95440505},
{"learn":[7.306431077],"iteration":36,"passed_time":0.1857364707,"remaining_time":4.834168144},
{"learn":[7.223863468],"iteration":37,"passed_time":0.1864061101,"remaining_time":4.71901784},
{"learn":[7.143477682],"iteration":38,"passed_time":0.1870884767,"remaining_time":4.610051951},
{"learn":[7.062817131],"iteration":39,"passed_time":0.1878127231,"remaining_time":4.507505354},
{"learn":[6.990793435],"iteration":40,"passed_time":0.1885184739,"remaining_time":4.409493084},
{"learn":[6.931862224],"iteration":41,"passed_time":0.1892561075,"remaining_time":4.316841691},
{"learn":[6.858296558],"iteration":42,"passed_time":0.1899075438,"remaining_time":4.226546962},
{"learn":[6.786268161],"iteration":43,"passed_time":0.1905159896,"remaining_time":4.139392865},
{"learn":[6.717118549],"iteration":44,"passed_time":0.191378843,"remaining_time":4.061484336},
{"learn":[6.652948106],"iteration":45,"passed_time":0.1923468457,"remaining_time":3.989106322},
{"learn":[6.589686076],"iteration":46,"passed_time":0.193039366,"remaining_time":3.914181188},
{"learn":[6.531283097],"iteration":47,"passed_time":0.1938146406,"remaining_time":3.843990372},
{"learn":[6.471368031],"iteration":48,"passed_time":0.1945511104,"remaining_time":3.775879715},
{"learn":[6.416481395],"iteration":49,"passed_time":0.1953445518,"remaining_time":3.711546484},
{"learn":[6.369870822],"iteration":50,"passed_time":0.1960782658,"remaining_time":3.648593613},
{"learn":[6.325678067],"iteration":51,"passed_time":0.196785532,"remaining_time":3.587551622},
{"learn":[6.275766122],"iteration":52,"passed_time":0.1974515587,"remaining_time":3.528049548},
{"learn":[6.224773967],"iteration":53,"passed_time":0.1981406242,"remaining_time":3.471130194},
{"learn":[6.182249254],"iteration":54,"passed_time":0.1987707656,"remaining_time":3.415243155},
{"learn":[6.139904173],"iteration":55,"passed_time":0.1994285575,"remaining_time":3.361795684},
{"learn":[6.100525536],"iteration":56,"passed_time":0.2003736164,"remaining_time":3.314952987},
{"learn":[6.062568564],"iteration":57,"passed_time":0.2013071223,"remaining_time":3.269505332},
{"learn":[6.030559288],"iteration":58,"passed_time":0.2022470166,"remaining_time":3.22566852},
{"learn":[5.997931376],"iteration":59,"passed_time":0.2029786366,"remaining_time":3.179998641},
{"learn":[5.964103835],"iteration":60,"passed_time":0.2035720268,"remaining_time":3.133674314},
{"learn":[5.933729724],"iteration":61,"passed_time":0.2041492693,"remaining_time":3.088580881},
{"learn":[5.901932711],"iteration":62,"passed_time":0.2047319663,"remaining_time":3.044981785},
{"learn":[5.873727795],"iteration":63,"passed_time":0.2053286508,"remaining_time":3.002931517},
{"learn":[5.846485734],"iteration":64,"passed_time":0.2061385214,"remaining_time":2.965223346},
{"learn":[5.820630862],"iteration":65,"passed_time":0.2071610794,"remaining_time":2.931643154},
{"learn":[5.793646238],"iteration":66,"passed_time":0.2080905536,"remaining_time":2.897738604},
{"learn":[5.765388646],"iteration":67,"passed_time":0.2093063294,"remaining_time":2.868727926},
{"learn":[5.747073912],"iteration":68,"passed_time":0.2102265216,"remaining_time":2.836534661},
{"learn":[5.722315217],"iteration":69,"passed_time":0.2109254585,"remaining_time":2.802295377},
{"learn":[5.699970599],"iteration":70,"passed_time":0.2116315079,"remaining_time":2.769093956},
{"learn":[5.682732647],"iteration":71,"passed_time":0.212257898,"remaining_time":2.735768463},
{"learn":[5.663525791],"iteration":72,"passed_time":0.2129391818,"remaining_time":2.704035911},
{"learn":[5.642381613],"iteration":73,"passed_time":0.2135599254,"remaining_time":2.672385013},
{"learn":[5.621404779],"iteration":74,"passed_time":0.2142734374,"remaining_time":2.642705728},
{"learn":[5.602460129],"iteration":75,"passed_time":0.2151743586,"remaining_time":2.616067202},
{"learn":[5.587337574],"iteration":76,"passed_time":0.2159752335,"remaining_time":2.588897929},
{"learn":[5.572393026],"iteration":77,"passed_time":0.216723449,"remaining_time":2.561782307},
{"learn":[5.558425806],"iteration":78,"passed_time":0.2173539242,"remaining_time":2.533961572},
{"learn":[5.541518902],"iteration":79,"passed_time":0.2180226115,"remaining_time":2.507260032},
{"learn":[5.526157283],"iteration":80,"passed_time":0.2186054437,"remaining_time":2.480227195},
{"learn":[5.511746977],"iteration":81,"passed_time":0.2192273347,"remaining_time":2.454276748},
{"learn":[5.504975022],"iteration":82,"passed_time":0.2195212254,"remaining_time":2.425312816},
{"learn":[5.493980522],"iteration":83,"passed_time":0.2202364645,"remaining_time":2.401626209},
{"learn":[5.480745463],"iteration":84,"passed_time":0.2210535867,"remaining_time":2.379576845},
{"learn":[5.464052013],"iteration":85,"passed_time":0.2224962106,"remaining_time":2.364669029},
{"learn":[5.449143727],"iteration":86,"passed_time":0.2237326389,"remaining_time":2.347906889},
{"learn":[5.438255432],"iteration":87,"passed_time":0.2247111316,"remaining_time":2.328824455},
{"learn":[5.425927931],"iteration":88,"passed_time":0.2254658112,"remaining_time":2.30785791},
{"learn":[5.412331217],"iteration":89,"passed_time":0.2260956461,"remaining_time":2.2860782},
{"learn":[5.400691499],"iteration":90,"passed_time":0.2267208682,"remaining_time":2.264717244},
{"learn":[5.391618744],"iteration":91,"passed_time":0.2273892424,"remaining_time":2.244232958},
{"learn":[5.380766572],"iteration":92,"passed_time":0.2280744094,"remaining_time":2.224338595},
{"learn":[5.372207183],"iteration":93,"passed_time":0.2289048461,"remaining_time":2.206253091},
{"learn":[5.362918837],"iteration":94,"passed_time":0.2296306724,"remaining_time":2.1875343},
{"learn":[5.348292324],"iteration":95,"passed_time":0.2304090945,"remaining_time":2.169685639},
{"learn":[5.339772295],"iteration":96,"passed_time":0.2310614716,"remaining_time":2.151015555},
{"learn":[5.331515983],"iteration":97,"passed_time":0.2316689794,"remaining_time":2.132300198},
{"learn":[5.323861644],"iteration":98,"passed_time":0.2322711245,"remaining_time":2.11390185},
{"learn":[5.313277281],"iteration":99,"passed_time":0.2328816474,"remaining_time":2.095934827},
{"learn":[5.30685627],"iteration":100,"passed_time":0.2335259458,"remaining_time":2.078612132},
{"learn":[5.29652059],"iteration":101,"passed_time":0.2342731819,"remaining_time":2.062522719},
{"learn":[5.288350766],"iteration":102,"passed_time":0.2349047726,"remaining_time":2.045724087},
{"learn":[5.27993346],"iteration":103,"passed_time":0.235506043,"remaining_time":2.028975139},
{"learn":[5.271789139],"iteration":104,"passed_time":0.2363254163,"remaining_time":2.014392834},
{"learn":[5.262684686],"iteration":105,"passed_time":0.2384095543,"remaining_time":2.010737184},
{"learn":[5.251619772],"iteration":106,"passed_time":0.2394104514,"remaining_time":1.998070403},
{"learn":[5.241012171],"iteration":107,"passed_time":0.2400935372,"remaining_time":1.98299477},
{"learn":[5.232684032],"iteration":108,"passed_time":0.2409331305,"remaining_time":1.969462562},
{"learn":[5.224267141],"iteration":109,"passed_time":0.241683483,"remaining_time":1.95543909},
{"learn":[5.216324968],"iteration":110,"passed_time":0.2424041568,"remaining_time":1.941417076},
{"learn":[5.211102527],"iteration":111,"passed_time":0.2430534853,"remaining_time":1.927066919},
{"learn":[5.206364257],"iteration":112,"passed_time":0.2436782276,"remaining_time":1.912766265},
{"learn":[5.196937641],"iteration":113,"passed_time":0.2444798681,"remaining_time":1.900080379},
{"learn":[5.190746047],"iteration":114,"passed_time":0.2451824156,"remaining_time":1.88683859},
{"learn":[5.181885213],"iteration":115,"passed_time":0.2459612385,"remaining_time":1.874394266},
{"learn":[5.178293568],"iteration":116,"passed_time":0.2465727842,"remaining_time":1.86088691},
{"learn":[5.170991438],"iteration":117,"passed_time":0.2472083131,"remaining_time":1.847777391},
{"learn":[5.166257212],"iteration":118,"passed_time":0.2478516081,"remaining_time":1.834935015},
{"learn":[5.161421246],"iteration":119,"passed_time":0.2484852771,"remaining_time":1.822225365},
{"learn":[5.158223542],"iteration":120,"passed_time":0.2492326828,"remaining_time":1.810541555},
{"learn":[5.15470988],"iteration":121,"passed_time":0.2498373847,"remaining_time":1.798010031},
{"learn":[5.146388143],"iteration":122,"passed_time":0.2507170045,"remaining_time":1.787632626},
{"learn":[5.139529364],"iteration":123,"passed_time":0.2515771018,"remaining_time":1.777270493},
{"learn":[5.134276023],"iteration":124,"passed_time":0.2533936607,"remaining_time":1.773755625},
{"learn":[5.128536065],"iteration":125,"passed_time":0.2543764838,"remaining_time":1.764484499},
{"learn":[5.123300353],"iteration":126,"passed_time":0.255044317,"remaining_time":1.753178651},
{"learn":[5.116200518],"iteration":127,"passed_time":0.2557683984,"remaining_time":1.742422214},
{"learn":[5.108728704],"iteration":128,"passed_time":0.2569316049,"remaining_time":1.734786263},
{"learn":[5.104075866],"iteration":129,"passed_time":0.257697502,"remaining_time":1.724590975},
{"learn":[5.100317606],"iteration":130,"passed_time":0.2585002253,"remaining_time":1.714783937},
{"learn":[5.095814182],"iteration":131,"passed_time":0.2594584663,"remaining_time":1.706135975},
{"learn":[5.092146915],"iteration":132,"passed_time":0.2602556197,"remaining_time":1.696553551},
{"learn":[5.085258329],"iteration":133,"passed_time":0.2610472392,"remaining_time":1.687066486},
{"learn":[5.079219421],"iteration":134,"passed_time":0.261834513,"remaining_time":1.677680398},
{"learn":[5.076476829],"iteration":135,"passed_time":0.2625333547,"remaining_time":1.667858959},
{"learn":[5.072133867],"iteration":136,"passed_time":0.2633341142,"remaining_time":1.658812705},
{"learn":[5.067031564],"iteration":137,"passed_time":0.264122185,"remaining_time":1.649806692},
{"learn":[5.061358312],"iteration":138,"passed_time":0.2648827087,"remaining_time":1.640748289},
{"learn":[5.056759124],"iteration":139,"passed_time":0.2656208734,"remaining_time":1.63167108},
{"learn":[5.050254],"iteration":140,"passed_time":0.2664340904,"remaining_time":1.623169388},
{"learn":[5.048376474],"iteration":141,"passed_time":0.267523445,"remaining_time":1.616444477},
{"learn":[5.042603751],"iteration":142,"passed_time":0.26845567,"remaining_time":1.608856707},
{"learn":[5.037477349],"iteration":143,"passed_time":0.2691399568,"remaining_time":1.599887521},
{"learn":[5.03230489],"iteration":144,"passed_time":0.2698122891,"remaining_time":1.590962119},
{"learn":[5.025976187],"iteration":145,"passed_time":0.2704443798,"remaining_time":1.581914386},
{"learn":[5.01952451],"iteration":146,"passed_time":0.2711204142,"remaining_time":1.573236145},
{"learn":[5.017569424],"iteration":147,"passed_time":0.2717592101,"remaining_time":1.564451669},
{"learn":[5.008962367],"iteration":148,"passed_time":0.2725050938,"remaining_time":1.556388153},
{"learn":[5.003880266],"iteration":149,"passed_time":0.2731678137,"remaining_time":1.547950944},
{"learn":[4.996387564],"iteration":150,"passed_time":0.2739906067,"remaining_time":1.540516722},
{"learn":[4.993361683],"iteration":151,"passed_time":0.2748276563,"remaining_time":1.53324903},
{"learn":[4.99005752],"iteration":152,"passed_time":0.2756366795,"remaining_time":1.525910245},
{"learn":[4.986908764],"iteration":153,"passed_time":0.2763175331,"remaining_time":1.517952162},
{"learn":[4.985207175],"iteration":154,"passed_time":0.2770414701,"remaining_time":1.510322853},
{"learn":[4.979003494],"iteration":155,"passed_time":0.2778467531,"remaining_time":1.503222177},
{"learn":[4.973142217],"iteration":156,"passed_time":0.2785604011,"remaining_time":1.49570967},
{"learn":[4.967056696],"iteration":157,"passed_time":0.2792741232,"remaining_time":1.488283619},
{"learn":[4.961460696],"iteration":158,"passed_time":0.2800556497,"remaining_time":1.481300638},
{"learn":[4.954240363],"iteration":159,"passed_time":0.2811154363,"remaining_time":1.47585604},
{"learn":[4.952320707],"iteration":160,"passed_time":0.2817220958,"remaining_time":1.468104586},
{"learn":[4.948337777],"iteration":161,"passed_time":0.2828543199,"remaining_time":1.46316},
{"learn":[4.943228639],"iteration":162,"passed_time":0.283861775,"remaining_time":1.457621507},
{"learn":[4.938545759],"iteration":163,"passed_time":0.2855087826,"remaining_time":1.455398428},
{"learn":[4.935330572],"iteration":164,"passed_time":0.2865380301,"remaining_time":1.450056092},
{"learn":[4.932051543],"iteration":165,"passed_time":0.287168571,"remaining_time":1.44276258},
{"learn":[4.928964153],"iteration":166,"passed_time":0.287969266,"remaining_time":1.436397596},
{"learn":[4.922860227],"iteration":167,"passed_time":0.2886190731,"remaining_time":1.4293516},
{"learn":[4.917668772],"iteration":168,"passed_time":0.289265372,"remaining_time":1.422364048},
{"learn":[4.910365386],"iteration":169,"passed_time":0.2899253241,"remaining_time":1.415517759},
{"learn":[4.906457206],"iteration":170,"passed_time":0.2905566141,"remaining_time":1.408604872},
{"learn":[4.901996508],"iteration":171,"passed_time":0.2912415334,"remaining_time":1.402023195},
{"learn":[4.896816173],"iteration":172,"passed_time":0.2920535832,"remaining_time":1.396117418},
{"learn":[4.891123132],"iteration":173,"passed_time":0.2927907148,"remaining_time":1.389914542},
{"learn":[4.887630202],"iteration":174,"passed_time":0.2935025082,"remaining_time":1.383654682},
{"learn":[4.885259712],"iteration":175,"passed_time":0.2941716347,"remaining_time":1.377258108},
{"learn":[4.880659728],"iteration":176,"passed_time":0.2948825658,"remaining_time":1.371120631},
{"learn":[4.877299723],"iteration":177,"passed_time":0.295600775,"remaining_time":1.365077736},
{"learn":[4.874038772],"iteration":178,"passed_time":0.2964831965,"remaining_time":1.35984751},
{"learn":[4.86943698],"iteration":179,"passed_time":0.2979470688,"remaining_time":1.357314425},
{"learn":[4.861268711],"iteration":180,"passed_time":0.2987794001,"remaining_time":1.351935518},
{"learn":[4.858673056],"iteration":181,"passed_time":0.2995201221,"remaining_time":1.346194835},
{"learn":[4.854036207],"iteration":182,"passed_time":0.3002265268,"remaining_time":1.340355587},
{"learn":[4.85130244],"iteration":183,"passed_time":0.3009482594,"remaining_time":1.334640107},
{"learn":[4.847510084],"iteration":184,"passed_time":0.3016978241,"remaining_time":1.329101225},
{"learn":[4.845691673],"iteration":185,"passed_time":0.3026434785,"remaining_time":1.324471997},
{"learn":[4.842058646],"iteration":186,"passed_time":0.3036633899,"remaining_time":1.320205005},
{"learn":[4.838623675],"iteration":187,"passed_time":0.3043403268,"remaining_time":1.314491199},
{"learn":[4.834602161],"iteration":188,"passed_time":0.3050674564,"remaining_time":1.309046069},
{"learn":[4.830858976],"iteration":189,"passed_time":0.3063293034,"remaining_time":1.305930188},
{"learn":[4.827590511],"iteration":190,"passed_time":0.3074561632,"remaining_time":1.302261969},
{"learn":[4.822246226],"iteration":191,"passed_time":0.3088517368,"remaining_time":1.299751059},
{"learn":[4.816686395],"iteration":192,"passed_time":0.3104881236,"remaining_time":1.298258631},
{"learn":[4.814797121],"iteration":193,"passed_time":0.3118041951,"remaining_time":1.295433924},
{"learn":[4.811639392],"iteration":194,"passed_time":0.3133137892,"remaining_time":1.293423591},
{"learn":[4.804813432],"iteration":195,"passed_time":0.3145873092,"remaining_time":1.290449983},
{"learn":[4.80251613],"iteration":196,"passed_time":0.3158340029,"remaining_time":1.287384286},
{"learn":[4.800087884],"iteration":197,"passed_time":0.3167593457,"remaining_time":1.28303533},
{"learn":[4.794773135],"iteration":198,"passed_time":0.3174767008,"remaining_time":1.277883605},
{"learn":[4.791664833],"iteration":199,"passed_time":0.318278821,"remaining_time":1.273115284},
{"learn":[4.785989873],"iteration":200,"passed_time":0.3189632919,"remaining_time":1.267918757},
{"learn":[4.782387142],"iteration":201,"passed_time":0.3197785145,"remaining_time":1.263283438},
{"learn":[4.778623704],"iteration":202,"passed_time":0.3205669554,"remaining_time":1.258580608},
{"learn":[4.775772178],"iteration":203,"passed_time":0.3211923616,"remaining_time":1.253279999},
{"learn":[4.77023101],"iteration":204,"passed_time":0.3219715405,"remaining_time":1.24862134},
{"learn":[4.764496689],"iteration":205,"passed_time":0.3227923714,"remaining_time":1.244160888},
{"learn":[4.763138716],"iteration":206,"passed_time":0.3234737036,"remaining_time":1.239201193},
{"learn":[4.758053283],"iteration":207,"passed_time":0.3241391057,"remaining_time":1.234221979},
{"learn":[4.755063788],"iteration":208,"passed_time":0.3248341667,"remaining_time":1.229396296},
{"learn":[4.752465267],"iteration":209,"passed_time":0.3255881006,"remaining_time":1.224831426},
{"learn":[4.748067377],"iteration":210,"passed_time":0.3265643905,"remaining_time":1.221134143},
{"learn":[4.744163298],"iteration":211,"passed_time":0.3281912612,"remaining_time":1.219880726},
{"learn":[4.736670896],"iteration":212,"passed_time":0.3290958783,"remaining_time":1.215955194},
{"learn":[4.73349255],"iteration":213,"passed_time":0.330138126,"remaining_time":1.212563397},
{"learn":[4.731864595],"iteration":214,"passed_time":0.3310016652,"remaining_time":1.208540963},
{"learn":[4.728398311],"iteration":215,"passed_time":0.3316880192,"remaining_time":1.203904662},
{"learn":[4.723865975],"iteration":216,"passed_time":0.332355768,"remaining_time":1.199237633},
{"learn":[4.723483365],"iteration":217,"passed_time":0.3329606147,"remaining_time":1.194381655},
{"learn":[4.72095416],"iteration":218,"passed_time":0.3336562738,"remaining_time":1.189888356},
{"learn":[4.716173382],"iteration":219,"passed_time":0.3343726383,"remaining_time":1.18550299},
{"learn":[4.710563974],"iteration":220,"passed_time":0.3352486458,"remaining_time":1.181713552},
{"learn":[4.707160263],"iteration":221,"passed_time":0.3360095045,"remaining_time":1.177546822},
{"learn":[4.70408351],"iteration":222,"passed_time":0.3367147015,"remaining_time":1.173216695},
{"learn":[4.702501831],"iteration":223,"passed_time":0.3375521573,"remaining_time":1.169377116},
{"learn":[4.700269738],"iteration":224,"passed_time":0.3382389638,"remaining_time":1.16504532},
{"learn":[4.695346302],"iteration":225,"passed_time":0.3389358388,"remaining_time":1.160780262},
{"learn":[4.689769299],"iteration":226,"passed_time":0.3396486841,"remaining_time":1.156601025},
{"learn":[4.687919514],"iteration":227,"passed_time":0.3403424923,"remaining_time":1.152387737},
{"learn":[4.682982074],"iteration":228,"passed_time":0.3410569936,"remaining_time":1.148274856},
{"learn":[4.679578702],"iteration":229,"passed_time":0.3417627663,"remaining_time":1.144162305},
{"learn":[4.675751423],"iteration":230,"passed_time":0.3429789913,"remaining_time":1.141778547},
{"learn":[4.672710726],"iteration":231,"passed_time":0.3439407441,"remaining_time":1.138562463},
{"learn":[4.6690533],"iteration":232,"passed_time":0.3449229431,"remaining_time":1.135433036},
{"learn":[4.667595702],"iteration":233,"passed_time":0.3457453981,"remaining_time":1.131799038},
{"learn":[4.664241291],"iteration":234,"passed_time":0.3465155264,"remaining_time":1.128018628},
{"learn":[4.662246999],"iteration":235,"passed_time":0.347283053,"remaining_time":1.124255307},
{"learn":[4.658668443],"iteration":236,"passed_time":0.34812737,"remaining_time":1.120764486},
{"learn":[4.658017572],"iteration":237,"passed_time":0.3488022546,"remaining_time":1.116753437},
{"learn":[4.657656705],"iteration":238,"passed_time":0.3496065379,"remaining_time":1.113182324},
{"learn":[4.653242871],"iteration":239,"passed_time":0.3503676675,"remaining_time":1.109497614},
{"learn":[4.6507302],"iteration":240,"passed_time":0.3510932623,"remaining_time":1.105725253},
{"learn":[4.647671336],"iteration":241,"passed_time":0.3519653517,"remaining_time":1.102436928},
{"learn":[4.645506007],"iteration":242,"passed_time":0.3526018472,"remaining_time":1.098434561},
{"learn":[4.641297906],"iteration":243,"passed_time":0.3532024595,"remaining_time":1.094348604},
{"learn":[4.63798107],"iteration":244,"passed_time":0.3538065874,"remaining_time":1.090301933},
{"learn":[4.635062318],"iteration":245,"passed_time":0.3544151172,"remaining_time":1.086296741},
{"learn":[4.631606017],"iteration":246,"passed_time":0.3550576917,"remaining_time":1.082422842},
{"learn":[4.630215494],"iteration":247,"passed_time":0.3556907064,"remaining_time":1.078546013},
{"learn":[4.62729814],"iteration":248,"passed_time":0.3563056143,"remaining_time":1.074640628},
{"learn":[4.624691756],"iteration":249,"passed_time":0.3570416217,"remaining_time":1.071124865},
{"learn":[4.621840053],"iteration":250,"passed_time":0.3580649295,"remaining_time":1.068488575},
{"learn":[4.619602091],"iteration":251,"passed_time":0.3588952189,"remaining_time":1.065292158},
{"learn":[4.613584029],"iteration":252,"passed_time":0.3596617236,"remaining_time":1.061926117},
{"learn":[4.6119388],"iteration":253,"passed_time":0.3613970375,"remaining_time":1.061425945},
{"learn":[4.60870702],"iteration":254,"passed_time":0.3628474432,"remaining_time":1.060083707},
{"learn":[4.604771557],"iteration":255,"passed_time":0.36349656,"remaining_time":1.056411877},
{"learn":[4.604231277],"iteration":256,"passed_time":0.3640741508,"remaining_time":1.052556786},
{"learn":[4.600750354],"iteration":257,"passed_time":0.3646505045,"remaining_time":1.048723544},
{"learn":[4.596488253],"iteration":258,"passed_time":0.3652114518,"remaining_time":1.044871374},
{"learn":[4.59470784],"iteration":259,"passed_time":0.3658970233,"remaining_time":1.04139922},
{"learn":[4.588818005],"iteration":260,"passed_time":0.3666529585,"remaining_time":1.038147649},
{"learn":[4.585054174],"iteration":261,"passed_time":0.3672809596,"remaining_time":1.034554764},
{"learn":[4.581471435],"iteration":262,"passed_time":0.3678494277,"remaining_time":1.030817598},
{"learn":[4.577555199],"iteration":263,"passed_time":0.3684779743,"remaining_time":1.027271928},
{"learn":[4.57457145],"iteration":264,"passed_time":0.3690824455,"remaining_time":1.0236815},
{"learn":[4.573029224],"iteration":265,"passed_time":0.369682243,"remaining_time":1.020100625},
{"learn":[4.571326203],"iteration":266,"passed_time":0.3702789432,"remaining_time":1.016533578},
{"learn":[4.571019224],"iteration":267,"passed_time":0.3708667775,"remaining_time":1.012964482},
{"learn":[4.565766631],"iteration":268,"passed_time":0.3714881151,"remaining_time":1.009508595},
{"learn":[4.563383471],"iteration":269,"passed_time":0.3726844622,"remaining_time":1.007628361},
{"learn":[4.558165805],"iteration":270,"passed_time":0.3736894168,"remaining_time":1.00523832},
{"learn":[4.55629209],"iteration":271,"passed_time":0.3743955721,"remaining_time":1.002058737},
{"learn":[4.549383848],"iteration":272,"passed_time":0.3750539551,"remaining_time":0.9987700561},
{"learn":[4.546227503],"iteration":273,"passed_time":0.3756921277,"remaining_time":0.9954470244},
{"learn":[4.540620977],"iteration":274,"passed_time":0.3763172025,"remaining_time":0.9921089885},
{"learn":[4.532898237],"iteration":275,"passed_time":0.3768937535,"remaining_time":0.9886633245},
{"learn":[4.529757367],"iteration":276,"passed_time":0.3774658758,"remaining_time":0.9852268165},
{"learn":[4.52579294],"iteration":277,"passed_time":0.3780130048,"remaining_time":0.9817460053},
{"learn":[4.521572155],"iteration":278,"passed_time":0.3786009855,"remaining_time":0.9783917941},
{"learn":[4.518818099],"iteration":279,"passed_time":0.3792613732,"remaining_time":0.975243531},
{"learn":[4.514012334],"iteration":280,"passed_time":0.3798693442,"remaining_time":0.9719788558},
{"learn":[4.508331416],"iteration":281,"passed_time":0.3805353121,"remaining_time":0.9688806883},
{"learn":[4.506038537],"iteration":282,"passed_time":0.3812580948,"remaining_time":0.9659436536},
{"learn":[4.505805643],"iteration":283,"passed_time":0.3818535149,"remaining_time":0.9627011149},
{"learn":[4.501550352],"iteration":284,"passed_time":0.3824369775,"remaining_time":0.959447154},
{"learn":[4.494692643],"iteration":285,"passed_time":0.383062176,"remaining_time":0.9563160617},
{"learn":[4.489330245],"iteration":286,"passed_time":0.383704822,"remaining_time":0.9532457774},
{"learn":[4.484826955],"iteration":287,"passed_time":0.3843714074,"remaining_time":0.950251535},
{"learn":[4.478285428],"iteration":288,"passed_time":0.3849937071,"remaining_time":0.9471644489},
{"learn":[4.475311671],"iteration":289,"passed_time":0.3856069994,"remaining_time":0.9440723089},
{"learn":[4.471581298],"iteration":290,"passed_time":0.3862118739,"remaining_time":0.9409766961},
{"learn":[4.469164956],"iteration":291,"passed_time":0.3869499728,"remaining_time":0.938221167},
{"learn":[4.462068024],"iteration":292,"passed_time":0.3882245867,"remaining_time":0.9367740028},
{"learn":[4.458540976],"iteration":293,"passed_time":0.3890690798,"remaining_time":0.9342951373},
{"learn":[4.455757458],"iteration":294,"passed_time":0.3897785009,"remaining_time":0.931504553},
{"learn":[4.453027414],"iteration":295,"passed_time":0.390474141,"remaining_time":0.9286952542},
{"learn":[4.450659338],"iteration":296,"passed_time":0.3912002295,"remaining_time":0.9259722605},
{"learn":[4.444696901],"iteration":297,"passed_time":0.3918489753,"remaining_time":0.923080472},
{"learn":[4.442052813],"iteration":298,"passed_time":0.392452757,"remaining_time":0.9200982698},
{"learn":[4.440036756],"iteration":299,"passed_time":0.3930386743,"remaining_time":0.9170902401},
{"learn":[4.435017051],"iteration":300,"passed_time":0.3936321935,"remaining_time":0.9141159576},
{"learn":[4.429962125],"iteration":301,"passed_time":0.394336699,"remaining_time":0.9114139599},
{"learn":[4.427666256],"iteration":302,"passed_time":0.3950195912,"remaining_time":0.9086754292},
{"learn":[4.425030004],"iteration":303,"passed_time":0.3956529955,"remaining_time":0.9058371212},
{"learn":[4.422588771],"iteration":304,"passed_time":0.3962497804,"remaining_time":0.9029298274},
{"learn":[4.418936667],"iteration":305,"passed_time":0.396886601,"remaining_time":0.9001284348},
{"learn":[4.416887976],"iteration":306,"passed_time":0.3974733099,"remaining_time":0.8972280252},
{"learn":[4.413773354],"iteration":307,"passed_time":0.3981054101,"remaining_time":0.8944446226},
{"learn":[4.411129391],"iteration":308,"passed_time":0.3987099139,"remaining_time":0.8916134321},
{"learn":[4.40850819],"iteration":309,"passed_time":0.3993032673,"remaining_time":0.8887717884},
{"learn":[4.404880292],"iteration":310,"passed_time":0.3999579113,"remaining_time":0.8860803887},
{"learn":[4.404593827],"iteration":311,"passed_time":0.400522389,"remaining_time":0.8832032169},
{"learn":[4.402139942],"iteration":312,"passed_time":0.4011058012,"remaining_time":0.8803823815},
{"learn":[4.400284725],"iteration":313,"passed_time":0.4018467018,"remaining_time":0.8779198645},
{"learn":[4.395805521],"iteration":314,"passed_time":0.4030865228,"remaining_time":0.8765532322},
{"learn":[4.392838833],"iteration":315,"passed_time":0.4040758232,"remaining_time":0.8746451363},
{"learn":[4.389213061],"iteration":316,"passed_time":0.4047238675,"remaining_time":0.8720075758},
{"learn":[4.3861981],"iteration":317,"passed_time":0.4053400344,"remaining_time":0.8693141618},
{"learn":[4.385054234],"iteration":318,"passed_time":0.405915711,"remaining_time":0.866547333},
{"learn":[4.379364607],"iteration":319,"passed_time":0.406509394,"remaining_time":0.8638324622},
{"learn":[4.378387619],"iteration":320,"passed_time":0.4071090749,"remaining_time":0.8611434949},
{"learn":[4.375816727],"iteration":321,"passed_time":0.4076702613,"remaining_time":0.8583864507},
{"learn":[4.374600202],"iteration":322,"passed_time":0.4082913826,"remaining_time":0.8557686254},
{"learn":[4.37098897],"iteration":323,"passed_time":0.4091256317,"remaining_time":0.8536077996},
{"learn":[4.367418484],"iteration":324,"passed_time":0.409844209,"remaining_time":0.8512148956},
{"learn":[4.363584638],"iteration":325,"passed_time":0.4105260441,"remaining_time":0.8487562997},
{"learn":[4.360770706],"iteration":326,"passed_time":0.4111580313,"remaining_time":0.8462059789},
{"learn":[4.358675808],"iteration":327,"passed_time":0.4118536722,"remaining_time":0.8437977675},
{"learn":[4.354228195],"iteration":328,"passed_time":0.4125069597,"remaining_time":0.8413135865},
{"learn":[4.353773425],"iteration":329,"passed_time":0.4130861825,"remaining_time":0.8386901282},
{"learn":[4.351648009],"iteration":330,"passed_time":0.4137184349,"remaining_time":0.8361862023},
{"learn":[4.348209927],"iteration":331,"passed_time":0.4143638728,"remaining_time":0.8337200813},
{"learn":[4.345852733],"iteration":332,"passed_time":0.4149609824,"remaining_time":0.8311680938},
{"learn":[4.34237339],"iteration":333,"passed_time":0.4155539395,"remaining_time":0.828619532},
{"learn":[4.340814362],"iteration":334,"passed_time":0.4161884939,"remaining_time":0.8261652193},
{"learn":[4.339707068],"iteration":335,"passed_time":0.4169150068,"remaining_time":0.8239034659},
{"learn":[4.335430786],"iteration":336,"passed_time":0.4176462736,"remaining_time":0.8216601763},
{"learn":[4.33521887],"iteration":337,"passed_time":0.4188362373,"remaining_time":0.8203242281},
{"learn":[4.328507238],"iteration":338,"passed_time":0.419593796,"remaining_time":0.8181460151},
{"learn":[4.326140732],"iteration":339,"passed_time":0.4202020578,"remaining_time":0.8156863474},
{"learn":[4.323785636],"iteration":340,"passed_time":0.4207724462,"remaining_time":0.8131643461},
{"learn":[4.320632534],"iteration":341,"passed_time":0.4213485265,"remaining_time":0.8106647089},
{"learn":[4.31973724],"iteration":342,"passed_time":0.421887052,"remaining_time":0.8081043532},
{"learn":[4.318000924],"iteration":343,"passed_time":0.4224551209,"remaining_time":0.8056120911},
{"learn":[4.312713628],"iteration":344,"passed_time":0.4230873026,"remaining_time":0.803252705},
{"learn":[4.308220789],"iteration":345,"passed_time":0.4238126852,"remaining_time":0.8010794685},
{"learn":[4.305890947],"iteration":346,"passed_time":0.4244803298,"remaining_time":0.7988059232},
{"learn":[4.305137856],"iteration":347,"passed_time":0.4250548231,"remaining_time":0.7963670824},
{"learn":[4.304787172],"iteration":348,"passed_time":0.4256781845,"remaining_time":0.7940300805},
{"learn":[4.30350134],"iteration":349,"passed_time":0.426308969,"remaining_time":0.7917166568},
{"learn":[4.30293809],"iteration":350,"passed_time":0.4268807935,"remaining_time":0.7893038033},
{"learn":[4.299548459],"iteration":351,"passed_time":0.4274966352,"remaining_time":0.7869824421},
{"learn":[4.294768408],"iteration":352,"passed_time":0.428153061,"remaining_time":0.7847451289},
{"learn":[4.294581479],"iteration":353,"passed_time":0.4287452402,"remaining_time":0.7823995061},
{"learn":[4.292551604],"iteration":354,"passed_time":0.4293323246,"remaining_time":0.7800545053},
{"learn":[4.288628894],"iteration":355,"passed_time":0.4299630426,"remaining_time":0.777798313},
{"learn":[4.287802767],"iteration":356,"passed_time":0.4306917558,"remaining_time":0.7757277283},
{"learn":[4.284566905],"iteration":357,"passed_time":0.4314076712,"remaining_time":0.7736416896},
{"learn":[4.27890232],"iteration":358,"passed_time":0.4320489528,"remaining_time":0.7714300243},
{"learn":[4.276938023],"iteration":359,"passed_time":0.4329062707,"remaining_time":0.7696111479},
{"learn":[4.273425094],"iteration":360,"passed_time":0.434208138,"remaining_time":0.7685844881},
{"learn":[4.269726505],"iteration":361,"passed_time":0.4350139732,"remaining_time":0.7666820854},
{"learn":[4.265565857],"iteration":362,"passed_time":0.4356276204,"remaining_time":0.7644484689},
{"learn":[4.262117173],"iteration":363,"passed_time":0.4362348197,"remaining_time":0.7622124871},
{"learn":[4.259185148],"iteration":364,"passed_time":0.4367862898,"remaining_time":0.7598884768},
{"learn":[4.257668507],"iteration":365,"passed_time":0.4374041917,"remaining_time":0.7576892283},
{"learn":[4.253432436],"iteration":366,"passed_time":0.4381979817,"remaining_time":0.7558019685},
{"learn":[4.250216667],"iteration":367,"passed_time":0.4389495039,"remaining_time":0.7538480611},
{"learn":[4.24514828],"iteration":368,"passed_time":0.4396041468,"remaining_time":0.7517350043},
{"learn":[4.244015772],"iteration":369,"passed_time":0.4402050891,"remaining_time":0.749538395},
{"learn":[4.240329192],"iteration":370,"passed_time":0.4408211671,"remaining_time":0.7473760487},
{"learn":[4.236718014],"iteration":371,"passed_time":0.4414649129,"remaining_time":0.7452687239},
{"learn":[4.233495944],"iteration":372,"passed_time":0.4421040343,"remaining_time":0.7431614732},
{"learn":[4.230357491],"iteration":373,"passed_time":0.4429647792,"remaining_time":0.7414330262},
{"learn":[4.227381215],"iteration":374,"passed_time":0.4436142484,"remaining_time":0.7393570806},
{"learn":[4.226169067],"iteration":375,"passed_time":0.4442010967,"remaining_time":0.7371847987},
{"learn":[4.225963861],"iteration":376,"passed_time":0.4447705408,"remaining_time":0.734992167},
{"learn":[4.224346548],"iteration":377,"passed_time":0.4454291252,"remaining_time":0.7329548039},
{"learn":[4.222595381],"iteration":378,"passed_time":0.4461138302,"remaining_time":0.730967516},
{"learn":[4.219700938],"iteration":379,"passed_time":0.4472442858,"remaining_time":0.7297143611},
{"learn":[4.216356207],"iteration":380,"passed_time":0.4481670982,"remaining_time":0.7281244981},
{"learn":[4.214326494],"iteration":381,"passed_time":0.4492408813,"remaining_time":0.7267823681},
{"learn":[4.212901398],"iteration":382,"passed_time":0.4499788466,"remaining_time":0.7249006485},
{"learn":[4.211331091],"iteration":383,"passed_time":0.4506046039,"remaining_time":0.7228448855},
{"learn":[4.208624791],"iteration":384,"passed_time":0.4512618834,"remaining_time":0.7208469047},
{"learn":[4.204659106],"iteration":385,"passed_time":0.4519675321,"remaining_time":0.7189328101},
{"learn":[4.202968852],"iteration":386,"passed_time":0.4525894128,"remaining_time":0.7168922739},
{"learn":[4.197261935],"iteration":387,"passed_time":0.4532159104,"remaining_time":0.7148663329},
{"learn":[4.196934403],"iteration":388,"passed_time":0.4537950712,"remaining_time":0.7127732352},
{"learn":[4.192479929],"iteration":389,"passed_time":0.4543971357,"remaining_time":0.710723725},
{"learn":[4.190243116],"iteration":390,"passed_time":0.4549789484,"remaining_time":0.7086500757},
{"learn":[4.185852431],"iteration":391,"passed_time":0.4555981924,"remaining_time":0.7066420944},
{"learn":[4.180967944],"iteration":392,"passed_time":0.4562030408,"remaining_time":0.704618946},
{"learn":[4.178283162],"iteration":393,"passed_time":0.4567970675,"remaining_time":0.7025863525},
{"learn":[4.176341157],"iteration":394,"passed_time":0.4573975098,"remaining_time":0.7005708695},
{"learn":[4.176041504],"iteration":395,"passed_time":0.4579566294,"remaining_time":0.6984995055},
{"learn":[4.175564513],"iteration":396,"passed_time":0.4586598325,"remaining_time":0.696654607},
{"learn":[4.170830274],"iteration":397,"passed_time":0.4594397513,"remaining_time":0.6949314832},
{"learn":[4.167804808],"iteration":398,"passed_time":0.4601748282,"remaining_time":0.6931455432},
{"learn":[4.165860548],"iteration":399,"passed_time":0.4608575872,"remaining_time":0.6912863808},
{"learn":[4.160950571],"iteration":400,"passed_time":0.4616430251,"remaining_time":0.6895864639},
{"learn":[4.158544115],"iteration":401,"passed_time":0.46238806,"remaining_time":0.6878309948},
{"learn":[4.154448767],"iteration":402,"passed_time":0.463136587,"remaining_time":0.6860857132},
{"learn":[4.15197457],"iteration":403,"passed_time":0.4642686456,"remaining_time":0.6849111703},
{"learn":[4.149562679],"iteration":404,"passed_time":0.4649704326,"remaining_time":0.6831047096},
{"learn":[4.149327961],"iteration":405,"passed_time":0.4656182932,"remaining_time":0.6812247936},
{"learn":[4.147444889],"iteration":406,"passed_time":0.4663114927,"remaining_time":0.6794169905},
{"learn":[4.147254809],"iteration":407,"passed_time":0.4669831702,"remaining_time":0.6775834235},
{"learn":[4.144589165],"iteration":408,"passed_time":0.4676307455,"remaining_time":0.6757207105},
{"learn":[4.141691034],"iteration":409,"passed_time":0.4682407453,"remaining_time":0.6738098529},
{"learn":[4.138893468],"iteration":410,"passed_time":0.4688390642,"remaining_time":0.6718885859},
{"learn":[4.136964597],"iteration":411,"passed_time":0.4694105441,"remaining_time":0.6699354368},
{"learn":[4.133773523],"iteration":412,"passed_time":0.4699901528,"remaining_time":0.668000532},
{"learn":[4.131363444],"iteration":413,"passed_time":0.470587516,"remaining_time":0.6660973052},
{"learn":[4.130228592],"iteration":414,"passed_time":0.4712386891,"remaining_time":0.6642762244},
{"learn":[4.12884186],"iteration":415,"passed_time":0.4718344967,"remaining_time":0.6623830435},
{"learn":[4.12413494],"iteration":416,"passed_time":0.4724430956,"remaining_time":0.6605139682},
{"learn":[4.119422508],"iteration":417,"passed_time":0.4730659098,"remaining_time":0.6586707165},
{"learn":[4.117038244],"iteration":418,"passed_time":0.4737823355,"remaining_time":0.6569630953},
{"learn":[4.116067631],"iteration":419,"passed_time":0.4744165996,"remaining_time":0.6551467328},
{"learn":[4.110343455],"iteration":420,"passed_time":0.475044161,"remaining_time":0.6533267678},
{"learn":[4.105604544],"iteration":421,"passed_time":0.4757260743,"remaining_time":0.6515868979},
{"learn":[4.103390131],"iteration":422,"passed_time":0.4763645529,"remaining_time":0.6497927826},
{"learn":[4.096724402],"iteration":423,"passed_time":0.4769784756,"remaining_time":0.6479707593},
{"learn":[4.093431279],"iteration":424,"passed_time":0.477597143,"remaining_time":0.6461608406},
{"learn":[4.091412744],"iteration":425,"passed_time":0.4784380921,"remaining_time":0.6446560207},
{"learn":[4.091192901],"iteration":426,"passed_time":0.4794572172,"remaining_time":0.6433934086},
{"learn":[4.088994581],"iteration":427,"passed_time":0.4801111718,"remaining_time":0.6416439025},
{"learn":[4.087845355],"iteration":428,"passed_time":0.4808272906,"remaining_time":0.6399822447},
{"learn":[4.083650279],"iteration":429,"passed_time":0.481531885,"remaining_time":0.6383097081},
{"learn":[4.079840652],"iteration":430,"passed_time":0.4821588567,"remaining_time":0.6365391866},
{"learn":[4.075707828],"iteration":431,"passed_time":0.4827746455,"remaining_time":0.6347592561},
{"learn":[4.071345409],"iteration":432,"passed_time":0.4833446311,"remaining_time":0.6329247247},
{"learn":[4.067460475],"iteration":433,"passed_time":0.4839280643,"remaining_time":0.6311135585},
{"learn":[4.064914749],"iteration":434,"passed_time":0.4845166551,"remaining_time":0.6293147359},
{"learn":[4.063823175],"iteration":435,"passed_time":0.4851137237,"remaining_time":0.6275324316},
{"learn":[4.058898471],"iteration":436,"passed_time":0.4857027413,"remaining_time":0.6257451793},
{"learn":[4.054120355],"iteration":437,"passed_time":0.486317782,"remaining_time":0.6239967887},
{"learn":[4.052715901],"iteration":438,"passed_time":0.4869095272,"remaining_time":0.6222237922},
{"learn":[4.052114167],"iteration":439,"passed_time":0.4875124987,"remaining_time":0.6204704529},
{"learn":[4.051377267],"iteration":440,"passed_time":0.4882539569,"remaining_time":0.6188978728},
{"learn":[4.049275336],"iteration":441,"passed_time":0.4889407688,"remaining_time":0.6172600655},
{"learn":[4.047099198],"iteration":442,"passed_time":0.4896922368,"remaining_time":0.6157078462},
{"learn":[4.044348685],"iteration":443,"passed_time":0.4905436502,"remaining_time":0.6142843908},
{"learn":[4.042822379],"iteration":444,"passed_time":0.4911342849,"remaining_time":0.6125382655},
{"learn":[4.041258611],"iteration":445,"passed_time":0.4917226234,"remaining_time":0.6107944694},
{"learn":[4.040044254],"iteration":446,"passed_time":0.4923272724,"remaining_time":0.6090760216},
{"learn":[4.036860137],"iteration":447,"passed_time":0.4929410355,"remaining_time":0.6073737758},
{"learn":[4.036372284],"iteration":448,"passed_time":0.4939045734,"remaining_time":0.6061056123},
{"learn":[4.03368231],"iteration":449,"passed_time":0.4949997331,"remaining_time":0.6049996738},
{"learn":[4.032439519],"iteration":450,"passed_time":0.4957499161,"remaining_time":0.6034738447},
{"learn":[4.032008634],"iteration":451,"passed_time":0.4964242097,"remaining_time":0.6018594401},
{"learn":[4.030034932],"iteration":452,"passed_time":0.497049031,"remaining_time":0.600189448},
{"learn":[4.028173412],"iteration":453,"passed_time":0.4976478343,"remaining_time":0.5984927699},
{"learn":[4.023806097],"iteration":454,"passed_time":0.4982662978,"remaining_time":0.5968244666},
{"learn":[4.020239186],"iteration":455,"passed_time":0.4988529066,"remaining_time":0.5951227658},
{"learn":[4.017384838],"iteration":456,"passed_time":0.4994295929,"remaining_time":0.5934141552},
{"learn":[4.016468229],"iteration":457,"passed_time":0.5000278366,"remaining_time":0.5917359987},
{"learn":[4.014530169],"iteration":458,"passed_time":0.5006473895,"remaining_time":0.5900876639},
{"learn":[4.012884822],"iteration":459,"passed_time":0.5012682937,"remaining_time":0.5884453883},
{"learn":[4.008924707],"iteration":460,"passed_time":0.5018692762,"remaining_time":0.5867842514},
{"learn":[4.008286778],"iteration":461,"passed_time":0.5024552117,"remaining_time":0.5851101816},
{"learn":[4.006444202],"iteration":462,"passed_time":0.5030446611,"remaining_time":0.5834448877},
{"learn":[4.003284363],"iteration":463,"passed_time":0.5036936075,"remaining_time":0.5818529603},
{"learn":[3.999811484],"iteration":464,"passed_time":0.5043739238,"remaining_time":0.5803011811},
{"learn":[3.997483319],"iteration":465,"passed_time":0.5050305655,"remaining_time":0.5787260128},
{"learn":[3.99708333],"iteration":466,"passed_time":0.5056283811,"remaining_time":0.5770876384},
{"learn":[3.995860263],"iteration":467,"passed_time":0.506164004,"remaining_time":0.575383013},
{"learn":[3.994131111],"iteration":468,"passed_time":0.5067483306,"remaining_time":0.573738515},
{"learn":[3.993125499],"iteration":469,"passed_time":0.5073445493,"remaining_time":0.5721119385},
{"learn":[3.992954084],"iteration":470,"passed_time":0.5078923421,"remaining_time":0.5704353482},
{"learn":[3.990635743],"iteration":471,"passed_time":0.5084648978,"remaining_time":0.5687912416},
{"learn":[3.986678254],"iteration":472,"passed_time":0.5098278826,"remaining_time":0.5680323343},
{"learn":[3.986393291],"iteration":473,"passed_time":0.5106591696,"remaining_time":0.5666808507},
{"learn":[3.986152671],"iteration":474,"passed_time":0.5112565927,"remaining_time":0.5650730762},
{"learn":[3.985596662],"iteration":475,"passed_time":0.5117945069,"remaining_time":0.563404037},
{"learn":[3.983853457],"iteration":476,"passed_time":0.5123757832,"remaining_time":0.5617872843},
{"learn":[3.983263928],"iteration":477,"passed_time":0.5129573371,"remaining_time":0.5601751673},
{"learn":[3.980067202],"iteration":478,"passed_time":0.5135697365,"remaining_time":0.5586009033},
{"learn":[3.978115407],"iteration":479,"passed_time":0.5141304534,"remaining_time":0.5569746578},
{"learn":[3.972661644],"iteration":480,"passed_time":0.5147817014,"remaining_time":0.555450526},
{"learn":[3.969938254],"iteration":481,"passed_time":0.5153997377,"remaining_time":0.5538943239},
{"learn":[3.968211434],"iteration":482,"passed_time":0.51599755,"remaining_time":0.5523203589},
{"learn":[3.966113368],"iteration":483,"passed_time":0.5165697413,"remaining_time":0.5507231126},
{"learn":[3.962246044],"iteration":484,"passed_time":0.5171956744,"remaining_time":0.5491871594},
{"learn":[3.961319703],"iteration":485,"passed_time":0.5178551707,"remaining_time":0.5476904481},
{"learn":[3.96078191],"iteration":486,"passed_time":0.5184641948,"remaining_time":0.546144008},
{"learn":[3.958913633],"iteration":487,"passed_time":0.5192666761,"remaining_time":0.5448043815},
{"learn":[3.957428286],"iteration":488,"passed_time":0.5199092183,"remaining_time":0.5432998171},
{"learn":[3.952641965],"iteration":489,"passed_time":0.5205461651,"remaining_time":0.5417929473},
{"learn":[3.951486786],"iteration":490,"passed_time":0.5211789402,"remaining_time":0.5402852965},
{"learn":[3.94938344],"iteration":491,"passed_time":0.5217905894,"remaining_time":0.538759389},
{"learn":[3.947297924],"iteration":492,"passed_time":0.5224226457,"remaining_time":0.5372581773},
{"learn":[3.946284886],"iteration":493,"passed_time":0.5230513594,"remaining_time":0.5357570605},
{"learn":[3.943288204],"iteration":494,"passed_time":0.5236650914,"remaining_time":0.5342441842},
{"learn":[3.943076488],"iteration":495,"passed_time":0.5245431693,"remaining_time":0.533003543},
{"learn":[3.942347078],"iteration":496,"passed_time":0.5255158804,"remaining_time":0.5318601365},
{"learn":[3.940251541],"iteration":497,"passed_time":0.5262618567,"remaining_time":0.5304888595},
{"learn":[3.939011019],"iteration":498,"passed_time":0.5269842779,"remaining_time":0.5290964393},
{"learn":[3.938760512],"iteration":499,"passed_time":0.5276451275,"remaining_time":0.5276451275},
{"learn":[3.934522727],"iteration":500,"passed_time":0.5283252085,"remaining_time":0.5262161259},
{"learn":[3.930091193],"iteration":501,"passed_time":0.5289734013,"remaining_time":0.5247584738},
{"learn":[3.927671752],"iteration":502,"passed_time":0.5295931627,"remaining_time":0.5232759481},
{"learn":[3.927280041],"iteration":503,"passed_time":0.5303496717,"remaining_time":0.5219314229},
{"learn":[3.925987561],"iteration":504,"passed_time":0.5313118228,"remaining_time":0.5207907966},
{"learn":[3.921645957],"iteration":505,"passed_time":0.5321541739,"remaining_time":0.5195339168},
{"learn":[3.920333743],"iteration":506,"passed_time":0.5329515953,"remaining_time":0.5182349832},
{"learn":[3.918659461],"iteration":507,"passed_time":0.5336286322,"remaining_time":0.5168214312},
{"learn":[3.916124385],"iteration":508,"passed_time":0.5342308332,"remaining_time":0.5153385837},
{"learn":[3.913849268],"iteration":509,"passed_time":0.5348777939,"remaining_time":0.5139021941},
{"learn":[3.912826119],"iteration":510,"passed_time":0.5354963691,"remaining_time":0.5124417309},
{"learn":[3.910034145],"iteration":511,"passed_time":0.5361176128,"remaining_time":0.5109870997},
{"learn":[3.90792379],"iteration":512,"passed_time":0.5368486542,"remaining_time":0.5096399505},
{"learn":[3.907823851],"iteration":513,"passed_time":0.5374778348,"remaining_time":0.5081988866},
{"learn":[3.904527401],"iteration":514,"passed_time":0.5380985661,"remaining_time":0.5067530185},
{"learn":[3.903378283],"iteration":515,"passed_time":0.5389282425,"remaining_time":0.505506336},
{"learn":[3.902170135],"iteration":516,"passed_time":0.5401800789,"remaining_time":0.5046556637},
{"learn":[3.899435429],"iteration":517,"passed_time":0.5408580667,"remaining_time":0.5032694752},
{"learn":[3.897497505],"iteration":518,"passed_time":0.5415677231,"remaining_time":0.5019153658},
{"learn":[3.896426119],"iteration":519,"passed_time":0.5422154709,"remaining_time":0.5005065885},
{"learn":[3.896044669],"iteration":520,"passed_time":0.5429253717,"remaining_time":0.4991578754},
{"learn":[3.892795942],"iteration":521,"passed_time":0.5436611694,"remaining_time":0.4978353237},
{"learn":[3.892413888],"iteration":522,"passed_time":0.5442862199,"remaining_time":0.4964140094},
{"learn":[3.891738985],"iteration":523,"passed_time":0.5449435896,"remaining_time":0.4950250928},
{"learn":[3.88822057],"iteration":524,"passed_time":0.5455679402,"remaining_time":0.4936090888},
{"learn":[3.883837053],"iteration":525,"passed_time":0.5462601971,"remaining_time":0.4922572878},
{"learn":[3.881769742],"iteration":526,"passed_time":0.5469747368,"remaining_time":0.4909279896},
{"learn":[3.880356898],"iteration":527,"passed_time":0.5476149286,"remaining_time":0.4895345574},
{"learn":[3.879250273],"iteration":528,"passed_time":0.5482108044,"remaining_time":0.4881045158},
{"learn":[3.877174493],"iteration":529,"passed_time":0.5487644116,"remaining_time":0.4866401386},
{"learn":[3.875854201],"iteration":530,"passed_time":0.5493557863,"remaining_time":0.4852125495},
{"learn":[3.873189396],"iteration":531,"passed_time":0.549913795,"remaining_time":0.483758752},
{"learn":[3.871583368],"iteration":532,"passed_time":0.5504867779,"remaining_time":0.4823214358},
{"learn":[3.869622679],"iteration":533,"passed_time":0.551043169,"remaining_time":0.4808728778},
{"learn":[3.866860164],"iteration":534,"passed_time":0.5515954217,"remaining_time":0.4794240581},
{"learn":[3.864498444],"iteration":535,"passed_time":0.5521646719,"remaining_time":0.4779932981},
{"learn":[3.861416322],"iteration":536,"passed_time":0.5527532681,"remaining_time":0.4765824267},
{"learn":[3.860265769],"iteration":537,"passed_time":0.5533403641,"remaining_time":0.4751733238},
{"learn":[3.859328725],"iteration":538,"passed_time":0.5540453146,"remaining_time":0.4738680706},
{"learn":[3.858521278],"iteration":539,"passed_time":0.5551242693,"remaining_time":0.4728836368},
{"learn":[3.85599111],"iteration":540,"passed_time":0.5558371219,"remaining_time":0.4715882421},
{"learn":[3.852379816],"iteration":541,"passed_time":0.5565064937,"remaining_time":0.4702582548},
{"learn":[3.851327537],"iteration":542,"passed_time":0.5571158557,"remaining_time":0.4688801953},
{"learn":[3.847854898],"iteration":543,"passed_time":0.5577004892,"remaining_time":0.4674842336},
{"learn":[3.847083414],"iteration":544,"passed_time":0.558274253,"remaining_time":0.4660821745},
{"learn":[3.845397429],"iteration":545,"passed_time":0.5589166662,"remaining_time":0.4647402316},
{"learn":[3.841933528],"iteration":546,"passed_time":0.5595709504,"remaining_time":0.4634106774},
{"learn":[3.840996474],"iteration":547,"passed_time":0.5603113316,"remaining_time":0.4621546019},
{"learn":[3.838355966],"iteration":548,"passed_time":0.5611036426,"remaining_time":0.4609430652},
{"learn":[3.83342799],"iteration":549,"passed_time":0.5618659857,"remaining_time":0.4597085337},
{"learn":[3.828161535],"iteration":550,"passed_time":0.5625270781,"remaining_time":0.4583932088},
{"learn":[3.823502399],"iteration":551,"passed_time":0.563138343,"remaining_time":0.4570398146},
{"learn":[3.820068862],"iteration":552,"passed_time":0.5637753091,"remaining_time":0.4557098792},
{"learn":[3.817951642],"iteration":553,"passed_time":0.5644092035,"remaining_time":0.4543799725},
{"learn":[3.815785958],"iteration":554,"passed_time":0.5650347441,"remaining_time":0.4530458759},
{"learn":[3.81503012],"iteration":555,"passed_time":0.5656804053,"remaining_time":0.4517303956},
{"learn":[3.813529315],"iteration":556,"passed_time":0.5662654424,"remaining_time":0.4503691041},
{"learn":[3.808881326],"iteration":557,"passed_time":0.5668696026,"remaining_time":0.4490257426},
{"learn":[3.808740434],"iteration":558,"passed_time":0.5676150098,"remaining_time":0.4477964567},
{"learn":[3.80714352],"iteration":559,"passed_time":0.5682433438,"remaining_time":0.446476913},
{"learn":[3.80573346],"iteration":560,"passed_time":0.5688446088,"remaining_time":0.4451386511},
{"learn":[3.803370052],"iteration":561,"passed_time":0.5696600071,"remaining_time":0.4439698988},
{"learn":[3.803215211],"iteration":562,"passed_time":0.5708563389,"remaining_time":0.4430980819},
{"learn":[3.801309667],"iteration":563,"passed_time":0.571724917,"remaining_time":0.4419717443},
{"learn":[3.800003847],"iteration":564,"passed_time":0.5723798005,"remaining_time":0.4406817933},
{"learn":[3.798026138],"iteration":565,"passed_time":0.5730622762,"remaining_time":0.4394152436},
{"learn":[3.794745847],"iteration":566,"passed_time":0.5737130656,"remaining_time":0.4381265562},
{"learn":[3.794312041],"iteration":567,"passed_time":0.5744478301,"remaining_time":0.4369039835},
{"learn":[3.792205926],"iteration":568,"passed_time":0.5753583947,"remaining_time":0.4358162884},
{"learn":[3.788991061],"iteration":569,"passed_time":0.5761243593,"remaining_time":0.4346201307},
{"learn":[3.787391572],"iteration":570,"passed_time":0.576877284,"remaining_time":0.4334156827},
{"learn":[3.7826445],"iteration":571,"passed_time":0.5777509707,"remaining_time":0.4323031739},
{"learn":[3.781700331],"iteration":572,"passed_time":0.5785291206,"remaining_time":0.4311203045},
{"learn":[3.780045374],"iteration":573,"passed_time":0.5794392472,"remaining_time":0.4300367932},
{"learn":[3.775462644],"iteration":574,"passed_time":0.5804439226,"remaining_time":0.4290237689},
{"learn":[3.773711943],"iteration":575,"passed_time":0.5811402625,"remaining_time":0.4277838043},
{"learn":[3.772415806],"iteration":576,"passed_time":0.5818588819,"remaining_time":0.4265620573},
{"learn":[3.770170875],"iteration":577,"passed_time":0.5826167106,"remaining_time":0.425370678},
{"learn":[3.765166479],"iteration":578,"passed_time":0.5832214043,"remaining_time":0.4240694494},
{"learn":[3.763976102],"iteration":579,"passed_time":0.5838109877,"remaining_time":0.4227596808},
{"learn":[3.760761708],"iteration":580,"passed_time":0.5845753889,"remaining_time":0.4215784646},
{"learn":[3.758155662],"iteration":581,"passed_time":0.5859951624,"remaining_time":0.4208693778},
{"learn":[3.756844548],"iteration":582,"passed_time":0.587284739,"remaining_time":0.4200647275},
{"learn":[3.753098923],"iteration":583,"passed_time":0.5886777033,"remaining_time":0.4193320626},
{"learn":[3.751618946],"iteration":584,"passed_time":0.589676209,"remaining_time":0.4183173107},
{"learn":[3.751398464],"iteration":585,"passed_time":0.5903009844,"remaining_time":0.4170385795},
{"learn":[3.749920103],"iteration":586,"passed_time":0.590989727,"remaining_time":0.4158070822},
{"learn":[3.748237465],"iteration":587,"passed_time":0.5916400002,"remaining_time":0.4145504763},
{"learn":[3.746021536],"iteration":588,"passed_time":0.5923119734,"remaining_time":0.4133110715},
{"learn":[3.74417648],"iteration":589,"passed_time":0.5929085276,"remaining_time":0.4120211802},
{"learn":[3.738788389],"iteration":590,"passed_time":0.5937227563,"remaining_time":0.4108842763},
{"learn":[3.736021611],"iteration":591,"passed_time":0.5944299377,"remaining_time":0.4096746868},
{"learn":[3.734546151],"iteration":592,"passed_time":0.5950981783,"remaining_time":0.408440065},
{"learn":[3.733527479],"iteration":593,"passed_time":0.5958111571,"remaining_time":0.4072379289},
{"learn":[3.733026392],"iteration":594,"passed_time":0.5964278538,"remaining_time":0.4059719005},
{"learn":[3.730314752],"iteration":595,"passed_time":0.5970440922,"remaining_time":0.4047077403},
{"learn":[3.727342596],"iteration":596,"passed_time":0.5976654815,"remaining_time":0.4034492279},
{"learn":[3.725459604],"iteration":597,"passed_time":0.5983330028,"remaining_time":0.4022238581},
{"learn":[3.723158842],"iteration":598,"passed_time":0.598932982,"remaining_time":0.4009551348},
{"learn":[3.722362756],"iteration":599,"passed_time":0.5997615988,"remaining_time":0.3998410659},
{"learn":[3.721443615],"iteration":600,"passed_time":0.6010226166,"remaining_time":0.399015015},
{"learn":[3.720743486],"iteration":601,"passed_time":0.6022619549,"remaining_time":0.3981731861},
{"learn":[3.720215334],"iteration":602,"passed_time":0.6035392415,"remaining_time":0.397355023},
{"learn":[3.719436563],"iteration":603,"passed_time":0.6043390725,"remaining_time":0.3962223058},
{"learn":[3.715046574],"iteration":604,"passed_time":0.6050777774,"remaining_time":0.3950507803},
{"learn":[3.71443396],"iteration":605,"passed_time":0.6057562069,"remaining_time":0.3938414942},
{"learn":[3.712938941],"iteration":606,"passed_time":0.6064319898,"remaining_time":0.3926322438},
{"learn":[3.712814764],"iteration":607,"passed_time":0.6070363659,"remaining_time":0.3913787096},
{"learn":[3.71235348],"iteration":608,"passed_time":0.6076384849,"remaining_time":0.3901258581},
{"learn":[3.711223749],"iteration":609,"passed_time":0.6083081322,"remaining_time":0.388918314},
{"learn":[3.710755648],"iteration":610,"passed_time":0.609068897,"remaining_time":0.3877705416},
{"learn":[3.708668039],"iteration":611,"passed_time":0.6100869791,"remaining_time":0.3867871697},
{"learn":[3.705623591],"iteration":612,"passed_time":0.6108276394,"remaining_time":0.3856285423},
{"learn":[3.704045802],"iteration":613,"passed_time":0.6113987814,"remaining_time":0.3843647062},
{"learn":[3.699915209],"iteration":614,"passed_time":0.6119825207,"remaining_time":0.3831110089},
{"learn":[3.696182221],"iteration":615,"passed_time":0.612561289,"remaining_time":0.381856388},
{"learn":[3.694263278],"iteration":616,"passed_time":0.6131522067,"remaining_time":0.3806114994},
{"learn":[3.693810229],"iteration":617,"passed_time":0.6137254675,"remaining_time":0.3793578133},
{"learn":[3.690900932],"iteration":618,"passed_time":0.6144177248,"remaining_time":0.3781795689},
{"learn":[3.688020895],"iteration":619,"passed_time":0.6156654728,"remaining_time":0.3773433543},
{"learn":[3.685491894],"iteration":620,"passed_time":0.6168600584,"remaining_time":0.376473369},
{"learn":[3.684328128],"iteration":621,"passed_time":0.6181008588,"remaining_time":0.3756304255},
{"learn":[3.680640153],"iteration":622,"passed_time":0.6188469935,"remaining_time":0.3744868645},
{"learn":[3.678932783],"iteration":623,"passed_time":0.6196036915,"remaining_time":0.3733509423},
{"learn":[3.674167041],"iteration":624,"passed_time":0.620295957,"remaining_time":0.3721775742},
{"learn":[3.672200976],"iteration":625,"passed_time":0.6209627781,"remaining_time":0.3709905416},
{"learn":[3.670606604],"iteration":626,"passed_time":0.6215802395,"remaining_time":0.3697758044},
{"learn":[3.665506042],"iteration":627,"passed_time":0.6222152936,"remaining_time":0.3685733905},
{"learn":[3.664214007],"iteration":628,"passed_time":0.6229239007,"remaining_time":0.367416164},
{"learn":[3.66261643],"iteration":629,"passed_time":0.6236604396,"remaining_time":0.3662767661},
{"learn":[3.662118449],"iteration":630,"passed_time":0.6243936226,"remaining_time":0.3651366826},
{"learn":[3.660871366],"iteration":631,"passed_time":0.6250782242,"remaining_time":0.3639695989},
{"learn":[3.656695243],"iteration":632,"passed_time":0.6257017286,"remaining_time":0.3627686168},
{"learn":[3.654497801],"iteration":633,"passed_time":0.6263795419,"remaining_time":0.3616008081},
{"learn":[3.654189134],"iteration":634,"passed_time":0.6269602863,"remaining_time":0.3603787473},
{"learn":[3.653957699],"iteration":635,"passed_time":0.627549694,"remaining_time":0.3591636613},
{"learn":[3.651920725],"iteration":636,"passed_time":0.6281165106,"remaining_time":0.3579376662},
{"learn":[3.65106705],"iteration":637,"passed_time":0.6288815615,"remaining_time":0.3568262151},
{"learn":[3.650612844],"iteration":638,"passed_time":0.6297563989,"remaining_time":0.3557778717},
{"learn":[3.649884732],"iteration":639,"passed_time":0.6312556701,"remaining_time":0.3550813144},
{"learn":[3.646276182],"iteration":640,"passed_time":0.6327879743,"remaining_time":0.3544007531},
{"learn":[3.645808194],"iteration":641,"passed_time":0.6337132389,"remaining_time":0.3533790335},
{"learn":[3.645042989],"iteration":642,"passed_time":0.6343842121,"remaining_time":0.3522164288},
{"learn":[3.639864499],"iteration":643,"passed_time":0.6351648829,"remaining_time":0.3511159912},
{"learn":[3.637318478],"iteration":644,"passed_time":0.6360396462,"remaining_time":0.3500683324},
{"learn":[3.636344905],"iteration":645,"passed_time":0.636635161,"remaining_time":0.3488681842},
{"learn":[3.634754643],"iteration":646,"passed_time":0.6372059485,"remaining_time":0.347656414},
{"learn":[3.630724975],"iteration":647,"passed_time":0.6378201822,"remaining_time":0.3464702225},
{"learn":[3.629408252],"iteration":648,"passed_time":0.6384484563,"remaining_time":0.345293387},
{"learn":[3.62790646],"iteration":649,"passed_time":0.639186523,"remaining_time":0.3441773585},
{"learn":[3.627388973],"iteration":650,"passed_time":0.639823916,"remaining_time":0.3430085202},
{"learn":[3.625163557],"iteration":651,"passed_time":0.6404785968,"remaining_time":0.3418505394},
{"learn":[3.623701985],"iteration":652,"passed_time":0.6411746778,"remaining_time":0.3407160998},
{"learn":[3.622342639],"iteration":653,"passed_time":0.6417997837,"remaining_time":0.3395454513},
{"learn":[3.621130639],"iteration":654,"passed_time":0.6424880286,"remaining_time":0.338409725},
{"learn":[3.619125665],"iteration":655,"passed_time":0.6431272522,"remaining_time":0.3372496566},
{"learn":[3.618878783],"iteration":656,"passed_time":0.643741866,"remaining_time":0.3360783258},
{"learn":[3.616207429],"iteration":657,"passed_time":0.644342693,"remaining_time":0.3349015213},
{"learn":[3.61206486],"iteration":658,"passed_time":0.6458299699,"remaining_time":0.3341851589},
{"learn":[3.611955873],"iteration":659,"passed_time":0.6468714259,"remaining_time":0.3332367952},
{"learn":[3.610713743],"iteration":660,"passed_time":0.647724674,"remaining_time":0.3321916255},
{"learn":[3.610044025],"iteration":661,"passed_time":0.6484496367,"remaining_time":0.3310815366},
{"learn":[3.607342669],"iteration":662,"passed_time":0.6491600612,"remaining_time":0.3299652196},
{"learn":[3.602510618],"iteration":663,"passed_time":0.6498196275,"remaining_time":0.3288243898},
{"learn":[3.600492392],"iteration":664,"passed_time":0.6504845336,"remaining_time":0.3276876974},
{"learn":[3.597171065],"iteration":665,"passed_time":0.6512845379,"remaining_time":0.3266201737},
{"learn":[3.594358798],"iteration":666,"passed_time":0.6520232312,"remaining_time":0.3255228426},
{"learn":[3.593945251],"iteration":667,"passed_time":0.6526575661,"remaining_time":0.3243747185},
{"learn":[3.593607748],"iteration":668,"passed_time":0.6532511858,"remaining_time":0.3232079858},
{"learn":[3.592238714],"iteration":669,"passed_time":0.6538954577,"remaining_time":0.322067912},
{"learn":[3.590144654],"iteration":670,"passed_time":0.6544869358,"remaining_time":0.3209034305},
{"learn":[3.587151536],"iteration":671,"passed_time":0.6551070632,"remaining_time":0.319754638},
{"learn":[3.586070865],"iteration":672,"passed_time":0.655729149,"remaining_time":0.3186083681},
{"learn":[3.585102746],"iteration":673,"passed_time":0.6563775167,"remaining_time":0.3174763657},
{"learn":[3.584362847],"iteration":674,"passed_time":0.656989055,"remaining_time":0.3163280635},
{"learn":[3.581407561],"iteration":675,"passed_time":0.6576268666,"remaining_time":0.315193942},
{"learn":[3.57919422],"iteration":676,"passed_time":0.6582215111,"remaining_time":0.3140406914},
{"learn":[3.577632204],"iteration":677,"passed_time":0.6588598732,"remaining_time":0.3129098513},
{"learn":[3.573911195],"iteration":678,"passed_time":0.6596440115,"remaining_time":0.3118493781},
{"learn":[3.573408216],"iteration":679,"passed_time":0.6608910064,"remaining_time":0.3110075324},
{"learn":[3.571076482],"iteration":680,"passed_time":0.6619568893,"remaining_time":0.3100796589},
{"learn":[3.568177107],"iteration":681,"passed_time":0.6628064395,"remaining_time":0.3090505099},
{"learn":[3.564824621],"iteration":682,"passed_time":0.6634050107,"remaining_time":0.3079054003},
{"learn":[3.562475026],"iteration":683,"passed_time":0.6639857506,"remaining_time":0.3067536509},
{"learn":[3.561226889],"iteration":684,"passed_time":0.6645666758,"remaining_time":0.3056036538},
{"learn":[3.559383467],"iteration":685,"passed_time":0.6652166384,"remaining_time":0.3044869161},
{"learn":[3.555209766],"iteration":686,"passed_time":0.6657902036,"remaining_time":0.3033367303},
{"learn":[3.55345383],"iteration":687,"passed_time":0.6663955169,"remaining_time":0.3022026181},
{"learn":[3.552300968],"iteration":688,"passed_time":0.6669985372,"remaining_time":0.3010690059},
{"learn":[3.551253986],"iteration":689,"passed_time":0.667610743,"remaining_time":0.2999410585},
{"learn":[3.549807725],"iteration":690,"passed_time":0.6682283558,"remaining_time":0.2988170216},
{"learn":[3.547992926],"iteration":691,"passed_time":0.6688327492,"remaining_time":0.2976885647},
{"learn":[3.545438607],"iteration":692,"passed_time":0.6694417063,"remaining_time":0.2965636419},
{"learn":[3.543313763],"iteration":693,"passed_time":0.6700400918,"remaining_time":0.2954355448},
{"learn":[3.542962896],"iteration":694,"passed_time":0.6706494381,"remaining_time":0.2943137822},
{"learn":[3.539800465],"iteration":695,"passed_time":0.6712940491,"remaining_time":0.293208895},
{"learn":[3.53953187],"iteration":696,"passed_time":0.6718913883,"remaining_time":0.2920847785},
{"learn":[3.536332425],"iteration":697,"passed_time":0.6724917045,"remaining_time":0.2909634595},
{"learn":[3.534993327],"iteration":698,"passed_time":0.6732379091,"remaining_time":0.289906453},
{"learn":[3.531637011],"iteration":699,"passed_time":0.6743804264,"remaining_time":0.2890201827},
{"learn":[3.531040284],"iteration":700,"passed_time":0.6754243586,"remaining_time":0.2880911315},
{"learn":[3.529973872],"iteration":701,"passed_time":0.6772511267,"remaining_time":0.287494068},
{"learn":[3.527325183],"iteration":702,"passed_time":0.6784119559,"remaining_time":0.2866121635},
{"learn":[3.527200815],"iteration":703,"passed_time":0.6794882603,"remaining_time":0.2856939276},
{"learn":[3.523459911],"iteration":704,"passed_time":0.680393968,"remaining_time":0.284703859},
{"learn":[3.522729934],"iteration":705,"passed_time":0.6812623119,"remaining_time":0.2836984698},
{"learn":[3.522260582],"iteration":706,"passed_time":0.6818701146,"remaining_time":0.2825854931},
{"learn":[3.518641591],"iteration":707,"passed_time":0.6824935161,"remaining_time":0.2814803767},
{"learn":[3.516856405],"iteration":708,"passed_time":0.683145784,"remaining_time":0.2803884671},
{"learn":[3.515083413],"iteration":709,"passed_time":0.6837391245,"remaining_time":0.2792737269},
{"learn":[3.514671214],"iteration":710,"passed_time":0.6843049361,"remaining_time":0.2781492638},
{"learn":[3.512617621],"iteration":711,"passed_time":0.684952274,"remaining_time":0.2770593468},
{"learn":[3.510747971],"iteration":712,"passed_time":0.6855795724,"remaining_time":0.2759626049},
{"learn":[3.508149266],"iteration":713,"passed_time":0.6861931398,"remaining_time":0.2748616778},
{"learn":[3.504557165],"iteration":714,"passed_time":0.6868156628,"remaining_time":0.2737656838},
{"learn":[3.501367208],"iteration":715,"passed_time":0.687446243,"remaining_time":0.2726742081},
{"learn":[3.497593362],"iteration":716,"passed_time":0.6881664262,"remaining_time":0.2716193844},
{"learn":[3.496291169],"iteration":717,"passed_time":0.6887876944,"remaining_time":0.2705266432},
{"learn":[3.49330374],"iteration":718,"passed_time":0.6894280991,"remaining_time":0.2694426924},
{"learn":[3.490044385],"iteration":719,"passed_time":0.6900699784,"remaining_time":0.2683605472},
{"learn":[3.488891789],"iteration":720,"passed_time":0.6909798833,"remaining_time":0.267383339},
{"learn":[3.486869081],"iteration":721,"passed_time":0.6917042674,"remaining_time":0.2663348841},
{"learn":[3.486303638],"iteration":722,"passed_time":0.6923138722,"remaining_time":0.2652433507},
{"learn":[3.486035862],"iteration":723,"passed_time":0.6929173983,"remaining_time":0.2641508314},
{"learn":[3.482668951],"iteration":724,"passed_time":0.6934976411,"remaining_time":0.2630508294},
{"learn":[3.47820549],"iteration":725,"passed_time":0.6940439574,"remaining_time":0.261939455},
{"learn":[3.474392283],"iteration":726,"passed_time":0.6946201858,"remaining_time":0.2608408676},
{"learn":[3.472268163],"iteration":727,"passed_time":0.6951947482,"remaining_time":0.2597430927},
{"learn":[3.471209164],"iteration":728,"passed_time":0.6958322765,"remaining_time":0.2586701604},
{"learn":[3.470049971],"iteration":729,"passed_time":0.6964517397,"remaining_time":0.2575917393},
{"learn":[3.469078654],"iteration":730,"passed_time":0.697065276,"remaining_time":0.256512393},
{"learn":[3.468643292],"iteration":731,"passed_time":0.6976523588,"remaining_time":0.2554246341},
{"learn":[3.468134848],"iteration":732,"passed_time":0.6982174574,"remaining_time":0.2543302335},
{"learn":[3.467820182],"iteration":733,"passed_time":0.6988055994,"remaining_time":0.2532456259},
{"learn":[3.465776156],"iteration":734,"passed_time":0.6994367607,"remaining_time":0.2521778797},
{"learn":[3.463037608],"iteration":735,"passed_time":0.7000538987,"remaining_time":0.2511062898},
{"learn":[3.45965637],"iteration":736,"passed_time":0.7006731158,"remaining_time":0.250036675},
{"learn":[3.457275091],"iteration":737,"passed_time":0.7013403402,"remaining_time":0.248985324},
{"learn":[3.455522955],"iteration":738,"passed_time":0.7020139786,"remaining_time":0.247937278},
{"learn":[3.451270508],"iteration":739,"passed_time":0.7027096811,"remaining_time":0.2468979961},
{"learn":[3.450978947],"iteration":740,"passed_time":0.7033146329,"remaining_time":0.2458279216},
{"learn":[3.450608492],"iteration":741,"passed_time":0.7039092477,"remaining_time":0.2447555066},
{"learn":[3.448122004],"iteration":742,"passed_time":0.7045224528,"remaining_time":0.243690808},
{"learn":[3.445646714],"iteration":743,"passed_time":0.7051808126,"remaining_time":0.2426428603},
{"learn":[3.44411263],"iteration":744,"passed_time":0.7063831714,"remaining_time":0.2417821593},
{"learn":[3.443264164],"iteration":745,"passed_time":0.7071748401,"remaining_time":0.2407807096},
{"learn":[3.439521363],"iteration":746,"passed_time":0.7077880526,"remaining_time":0.2397193806},
{"learn":[3.436809225],"iteration":747,"passed_time":0.7083868861,"remaining_time":0.2386544055},
{"learn":[3.435509465],"iteration":748,"passed_time":0.7089588317,"remaining_time":0.2375816646},
{"learn":[3.434450277],"iteration":749,"passed_time":0.7095455336,"remaining_time":0.2365151779},
{"learn":[3.431786753],"iteration":750,"passed_time":0.7101567219,"remaining_time":0.2354580876},
{"learn":[3.430150302],"iteration":751,"passed_time":0.7107396419,"remaining_time":0.2343928606},
{"learn":[3.42696281],"iteration":752,"passed_time":0.7113393489,"remaining_time":0.2333344212},
{"learn":[3.426870334],"iteration":753,"passed_time":0.7119188827,"remaining_time":0.2322706169},
{"learn":[3.425200309],"iteration":754,"passed_time":0.7125174962,"remaining_time":0.2312142868},
{"learn":[3.423383783],"iteration":755,"passed_time":0.7131038568,"remaining_time":0.2301552131},
{"learn":[3.422752979],"iteration":756,"passed_time":0.7136937318,"remaining_time":0.2290985163},
{"learn":[3.420845924],"iteration":757,"passed_time":0.7143292611,"remaining_time":0.2280576269},
{"learn":[3.418917862],"iteration":758,"passed_time":0.7149661516,"remaining_time":0.2270182379},
{"learn":[3.417095735],"iteration":759,"passed_time":0.7157122007,"remaining_time":0.2260143792},
{"learn":[3.414391848],"iteration":760,"passed_time":0.7165161325,"remaining_time":0.2250293767},
{"learn":[3.41426711],"iteration":761,"passed_time":0.7174293908,"remaining_time":0.2240789961},
{"learn":[3.411976013],"iteration":762,"passed_time":0.7182132111,"remaining_time":0.2230885073},
{"learn":[3.408614844],"iteration":763,"passed_time":0.7190456248,"remaining_time":0.22211357},
{"learn":[3.407906721],"iteration":764,"passed_time":0.7196979432,"remaining_time":0.2210836819},
{"learn":[3.407494015],"iteration":765,"passed_time":0.7203342265,"remaining_time":0.2200498812},
{"learn":[3.406287128],"iteration":766,"passed_time":0.72111116,"remaining_time":0.2190598439},
{"learn":[3.404600442],"iteration":767,"passed_time":0.7223809977,"remaining_time":0.2182192597},
{"learn":[3.404012662],"iteration":768,"passed_time":0.7230241703,"remaining_time":0.2171893151},
{"learn":[3.400398762],"iteration":769,"passed_time":0.7237453788,"remaining_time":0.2161836846},
{"learn":[3.399737714],"iteration":770,"passed_time":0.7243468039,"remaining_time":0.2151432141},
{"learn":[3.399185251],"iteration":771,"passed_time":0.7249755932,"remaining_time":0.2141119628},
{"learn":[3.397245411],"iteration":772,"passed_time":0.7255549666,"remaining_time":0.2130672412},
{"learn":[3.396229831],"iteration":773,"passed_time":0.7261388916,"remaining_time":0.212025051},
{"learn":[3.394002836],"iteration":774,"passed_time":0.7267096858,"remaining_time":0.2109802314},
{"learn":[3.389617243],"iteration":775,"passed_time":0.7273381195,"remaining_time":0.2099532716},
{"learn":[3.385426488],"iteration":776,"passed_time":0.7279678291,"remaining_time":0.2089277038},
{"learn":[3.385072258],"iteration":777,"passed_time":0.7285900696,"remaining_time":0.2079010224},
{"learn":[3.383842366],"iteration":778,"passed_time":0.7291944676,"remaining_time":0.2068703175},
{"learn":[3.380110746],"iteration":779,"passed_time":0.7297710976,"remaining_time":0.2058328737},
{"learn":[3.378595218],"iteration":780,"passed_time":0.7303883939,"remaining_time":0.2048080132},
{"learn":[3.377371219],"iteration":781,"passed_time":0.7311394417,"remaining_time":0.2038214812},
{"learn":[3.375814782],"iteration":782,"passed_time":0.7317404069,"remaining_time":0.202793957},
{"learn":[3.374195887],"iteration":783,"passed_time":0.7323654826,"remaining_time":0.2017741636},
{"learn":[3.373704309],"iteration":784,"passed_time":0.7329661392,"remaining_time":0.2007486878},
{"learn":[3.372971757],"iteration":785,"passed_time":0.7335581214,"remaining_time":0.1997219313},
{"learn":[3.371565136],"iteration":786,"passed_time":0.7341173188,"remaining_time":0.1986874065},
{"learn":[3.3700309],"iteration":787,"passed_time":0.7346786941,"remaining_time":0.1976546741},
{"learn":[3.368186663],"iteration":788,"passed_time":0.7352216719,"remaining_time":0.1966182164},
{"learn":[3.366710398],"iteration":789,"passed_time":0.7358102726,"remaining_time":0.1955951358},
{"learn":[3.364598042],"iteration":790,"passed_time":0.7367674168,"remaining_time":0.1946705311},
{"learn":[3.36348442],"iteration":791,"passed_time":0.7374725096,"remaining_time":0.193679649},
{"learn":[3.362001759],"iteration":792,"passed_time":0.7380782455,"remaining_time":0.1926635521},
{"learn":[3.361580401],"iteration":793,"passed_time":0.7386909233,"remaining_time":0.1916502899},
{"learn":[3.359543675],"iteration":794,"passed_time":0.7393155271,"remaining_time":0.1906411108},
{"learn":[3.35766119],"iteration":795,"passed_time":0.7398708528,"remaining_time":0.1896151432},
{"learn":[3.354592969],"iteration":796,"passed_time":0.7404721475,"remaining_time":0.1886020652},
{"learn":[3.350985986],"iteration":797,"passed_time":0.7410587473,"remaining_time":0.1875862994},
{"learn":[3.349589624],"iteration":798,"passed_time":0.7417051173,"remaining_time":0.186586644},
{"learn":[3.349110856],"iteration":799,"passed_time":0.7423208127,"remaining_time":0.1855802032},
{"learn":[3.345315441],"iteration":800,"passed_time":0.7428844152,"remaining_time":0.184561796},
{"learn":[3.34397474],"iteration":801,"passed_time":0.7435116557,"remaining_time":0.1835602342},
{"learn":[3.343800902],"iteration":802,"passed_time":0.7441115624,"remaining_time":0.1825528989},
{"learn":[3.342329465],"iteration":803,"passed_time":0.7447694838,"remaining_time":0.1815607199},
{"learn":[3.34220347],"iteration":804,"passed_time":0.7453777369,"remaining_time":0.18055734},
{"learn":[3.341279219],"iteration":805,"passed_time":0.7459885746,"remaining_time":0.1795555626},
{"learn":[3.337329521],"iteration":806,"passed_time":0.7466732693,"remaining_time":0.1785724176},
{"learn":[3.336708453],"iteration":807,"passed_time":0.7473798572,"remaining_time":0.1775952136},
{"learn":[3.333252703],"iteration":808,"passed_time":0.7480761218,"remaining_time":0.1766162414},
{"learn":[3.332186769],"iteration":809,"passed_time":0.7487559476,"remaining_time":0.1756341112},
{"learn":[3.330594851],"iteration":810,"passed_time":0.7493801345,"remaining_time":0.1746397601},
{"learn":[3.327867442],"iteration":811,"passed_time":0.7499861132,"remaining_time":0.173642105},
{"learn":[3.327563111],"iteration":812,"passed_time":0.7505794422,"remaining_time":0.1726425039},
{"learn":[3.326308994],"iteration":813,"passed_time":0.7512103243,"remaining_time":0.171652482},
{"learn":[3.326249879],"iteration":814,"passed_time":0.7520070041,"remaining_time":0.1707009764},
{"learn":[3.322336238],"iteration":815,"passed_time":0.7527749804,"remaining_time":0.1697433779},
{"learn":[3.320491154],"iteration":816,"passed_time":0.7534720548,"remaining_time":0.1687703623},
{"learn":[3.320434271],"iteration":817,"passed_time":0.7541526975,"remaining_time":0.1677943655},
{"learn":[3.319609638],"iteration":818,"passed_time":0.7547837062,"remaining_time":0.1668081207},
{"learn":[3.316182682],"iteration":819,"passed_time":0.7553626445,"remaining_time":0.1658113122},
{"learn":[3.313126612],"iteration":820,"passed_time":0.755971262,"remaining_time":0.1648219926},
{"learn":[3.311222803],"iteration":821,"passed_time":0.7565485124,"remaining_time":0.1638268068},
{"learn":[3.309627335],"iteration":822,"passed_time":0.7571512283,"remaining_time":0.1628381135},
{"learn":[3.307974895],"iteration":823,"passed_time":0.7577547924,"remaining_time":0.1618505382},
{"learn":[3.307321505],"iteration":824,"passed_time":0.7583748235,"remaining_time":0.1608673868},
{"learn":[3.306759087],"iteration":825,"passed_time":0.7590422237,"remaining_time":0.1598950931},
{"learn":[3.30484037],"iteration":826,"passed_time":0.7597108787,"remaining_time":0.1589237993},
{"learn":[3.30201994],"iteration":827,"passed_time":0.7603403869,"remaining_time":0.1579451045},
{"learn":[3.299302297],"iteration":828,"passed_time":0.7609539051,"remaining_time":0.1569639539},
{"learn":[3.298132671],"iteration":829,"passed_time":0.7616974283,"remaining_time":0.1560103166},
{"learn":[3.296976183],"iteration":830,"passed_time":0.7623494986,"remaining_time":0.1550385864},
{"learn":[3.293144745],"iteration":831,"passed_time":0.7629520254,"remaining_time":0.1540576205},
{"learn":[3.290284404],"iteration":832,"passed_time":0.7635870088,"remaining_time":0.1530840702},
{"learn":[3.288285745],"iteration":833,"passed_time":0.7641993524,"remaining_time":0.1521068255},
{"learn":[3.286662667],"iteration":834,"passed_time":0.7648176964,"remaining_time":0.1511316406},
{"learn":[3.285692682],"iteration":835,"passed_time":0.7654395402,"remaining_time":0.1501579959},
{"learn":[3.284565611],"iteration":836,"passed_time":0.7660364584,"remaining_time":0.1491803378},
{"learn":[3.283897383],"iteration":837,"passed_time":0.7667985781,"remaining_time":0.1482355246},
{"learn":[3.280712855],"iteration":838,"passed_time":0.7678482833,"remaining_time":0.1473463333},
{"learn":[3.280468341],"iteration":839,"passed_time":0.7685972983,"remaining_time":0.1463994854},
{"learn":[3.277814895],"iteration":840,"passed_time":0.7693763647,"remaining_time":0.1454587895},
{"learn":[3.276316385],"iteration":841,"passed_time":0.7699867052,"remaining_time":0.1444868164},
{"learn":[3.27557063],"iteration":842,"passed_time":0.7705771109,"remaining_time":0.1435119886},
{"learn":[3.27499628],"iteration":843,"passed_time":0.7711416229,"remaining_time":0.1425332858},
{"learn":[3.273569958],"iteration":844,"passed_time":0.7717017306,"remaining_time":0.1415547553},
{"learn":[3.269665595],"iteration":845,"passed_time":0.7722944565,"remaining_time":0.1405831517},
{"learn":[3.267984685],"iteration":846,"passed_time":0.7729072009,"remaining_time":0.1396160587},
{"learn":[3.267702508],"iteration":847,"passed_time":0.7736314419,"remaining_time":0.1386697868},
{"learn":[3.266671924],"iteration":848,"passed_time":0.7742882126,"remaining_time":0.1377120378},
{"learn":[3.265359825],"iteration":849,"passed_time":0.7749567279,"remaining_time":0.1367570696},
{"learn":[3.2618983],"iteration":850,"passed_time":0.7755498446,"remaining_time":0.1357895733},
{"learn":[3.260456253],"iteration":851,"passed_time":0.7762053258,"remaining_time":0.134833789},
{"learn":[3.258389147],"iteration":852,"passed_time":0.7769254718,"remaining_time":0.1338898527},
{"learn":[3.258108469],"iteration":853,"passed_time":0.7775392282,"remaining_time":0.1329282521},
{"learn":[3.256424936],"iteration":854,"passed_time":0.77815411,"remaining_time":0.1319676561},
{"learn":[3.254817983],"iteration":855,"passed_time":0.7787231609,"remaining_time":0.1310001579},
{"learn":[3.253898449],"iteration":856,"passed_time":0.7793477055,"remaining_time":0.1300428493},
{"learn":[3.253023652],"iteration":857,"passed_time":0.7799382112,"remaining_time":0.129080683},
{"learn":[3.252845542],"iteration":858,"passed_time":0.7805442015,"remaining_time":0.1281219237},
{"learn":[3.252316026],"iteration":859,"passed_time":0.7811447539,"remaining_time":0.1271630995},
{"learn":[3.24975301],"iteration":860,"passed_time":0.7818677405,"remaining_time":0.1262248733},
{"learn":[3.249151075],"iteration":861,"passed_time":0.7830572182,"remaining_time":0.1253618284},
{"learn":[3.246257135],"iteration":862,"passed_time":0.7838984154,"remaining_time":0.124442738},
{"learn":[3.243826471],"iteration":863,"passed_time":0.7845289663,"remaining_time":0.1234906706},
{"learn":[3.243190653],"iteration":864,"passed_time":0.785134019,"remaining_time":0.1225353671},
{"learn":[3.24008797],"iteration":865,"passed_time":0.7857151489,"remaining_time":0.1215771708},
{"learn":[3.240036811],"iteration":866,"passed_time":0.7862589047,"remaining_time":0.1206141111},
{"learn":[3.238676314],"iteration":867,"passed_time":0.7868704066,"remaining_time":0.1196623199},
{"learn":[3.237848782],"iteration":868,"passed_time":0.7874976929,"remaining_time":0.1187136913},
{"learn":[3.236405498],"iteration":869,"passed_time":0.7880474773,"remaining_time":0.1177542207},
{"learn":[3.233378068],"iteration":870,"passed_time":0.78870684,"remaining_time":0.1168119201},
{"learn":[3.233169169],"iteration":871,"passed_time":0.7892707268,"remaining_time":0.1158562535},
{"learn":[3.232434885],"iteration":872,"passed_time":0.7899769288,"remaining_time":0.1149221878},
{"learn":[3.229978115],"iteration":873,"passed_time":0.7906785127,"remaining_time":0.1139879778},
{"learn":[3.229648848],"iteration":874,"passed_time":0.791281195,"remaining_time":0.1130401707},
{"learn":[3.227208761],"iteration":875,"passed_time":0.79187567,"remaining_time":0.1120919898},
{"learn":[3.226258869],"iteration":876,"passed_time":0.7924732697,"remaining_time":0.1111450538},
{"learn":[3.225331995],"iteration":877,"passed_time":0.79309178,"remaining_time":0.1102018191},
{"learn":[3.221968268],"iteration":878,"passed_time":0.793681291,"remaining_time":0.1092553313},
{"learn":[3.221166317],"iteration":879,"passed_time":0.7943307416,"remaining_time":0.1083178284},
{"learn":[3.220047503],"iteration":880,"passed_time":0.7948793331,"remaining_time":0.107367356},
{"learn":[3.21982781],"iteration":881,"passed_time":0.7954624876,"remaining_time":0.106422419},
{"learn":[3.216693405],"iteration":882,"passed_time":0.7960816604,"remaining_time":0.1054830739},
{"learn":[3.214798761],"iteration":883,"passed_time":0.7966893717,"remaining_time":0.1045429492},
{"learn":[3.214395085],"iteration":884,"passed_time":0.7977291808,"remaining_time":0.1036597241},
{"learn":[3.213470696],"iteration":885,"passed_time":0.7986028316,"remaining_time":0.1027547661},
{"learn":[3.211595017],"iteration":886,"passed_time":0.7993618076,"remaining_time":0.1018352697},
{"learn":[3.210965255],"iteration":887,"passed_time":0.8000398273,"remaining_time":0.1009059242},
{"learn":[3.209413583],"iteration":888,"passed_time":0.8008162161,"remaining_time":0.0999894263},
{"learn":[3.208331683],"iteration":889,"passed_time":0.8016738748,"remaining_time":0.09908328789},
{"learn":[3.207110711],"iteration":890,"passed_time":0.8024213789,"remaining_time":0.0981637826},
{"learn":[3.204519413],"iteration":891,"passed_time":0.8030704295,"remaining_time":0.09723274258},
{"learn":[3.201421296],"iteration":892,"passed_time":0.8036708044,"remaining_time":0.09629650176},
{"learn":[3.200691259],"iteration":893,"passed_time":0.8043764444,"remaining_time":0.0953734934},
{"learn":[3.200485067],"iteration":894,"passed_time":0.8050873259,"remaining_time":0.09445158571},
{"learn":[3.197467568],"iteration":895,"passed_time":0.8057130683,"remaining_time":0.09352026685},
{"learn":[3.195838544],"iteration":896,"passed_time":0.8063531451,"remaining_time":0.0925912753},
{"learn":[3.195671746],"iteration":897,"passed_time":0.8069248144,"remaining_time":0.09165515709},
{"learn":[3.194213094],"iteration":898,"passed_time":0.8075302087,"remaining_time":0.09072363858},
{"learn":[3.192884691],"iteration":899,"passed_time":0.8081312144,"remaining_time":0.08979235716},
{"learn":[3.188364239],"iteration":900,"passed_time":0.8087353915,"remaining_time":0.08886215734},
{"learn":[3.185219478],"iteration":901,"passed_time":0.8093264142,"remaining_time":0.08793125121},
{"learn":[3.184120387],"iteration":902,"passed_time":0.8099776639,"remaining_time":0.08700756744},
{"learn":[3.183725321],"iteration":903,"passed_time":0.8106193806,"remaining_time":0.08608347405},
{"learn":[3.181264554],"iteration":904,"passed_time":0.8112686546,"remaining_time":0.08516079799},
{"learn":[3.180741589],"iteration":905,"passed_time":0.8120386624,"remaining_time":0.08425125195},
{"learn":[3.179782639],"iteration":906,"passed_time":0.8130529866,"remaining_time":0.08336706477},
{"learn":[3.176377564],"iteration":907,"passed_time":0.8138622302,"remaining_time":0.08246181187},
{"learn":[3.174078182],"iteration":908,"passed_time":0.8146286923,"remaining_time":0.08155248734},
{"learn":[3.171242379],"iteration":909,"passed_time":0.8152422104,"remaining_time":0.08062835048},
{"learn":[3.170421012],"iteration":910,"passed_time":0.8159811205,"remaining_time":0.07971714569},
{"learn":[3.170087224],"iteration":911,"passed_time":0.8165657155,"remaining_time":0.07879142869},
{"learn":[3.167303059],"iteration":912,"passed_time":0.8171407031,"remaining_time":0.07786554345},
{"learn":[3.16705966],"iteration":913,"passed_time":0.817681675,"remaining_time":0.07693722543},
{"learn":[3.165667683],"iteration":914,"passed_time":0.8182335016,"remaining_time":0.07601076245},
{"learn":[3.164689733],"iteration":915,"passed_time":0.8188990472,"remaining_time":0.07509554582},
{"learn":[3.163311455],"iteration":916,"passed_time":0.8195844905,"remaining_time":0.07418267471},
{"learn":[3.159425016],"iteration":917,"passed_time":0.8202764959,"remaining_time":0.07327088525},
{"learn":[3.159327058],"iteration":918,"passed_time":0.8208942807,"remaining_time":0.07235303236},
{"learn":[3.15819426],"iteration":919,"passed_time":0.8215091658,"remaining_time":0.07143557964},
{"learn":[3.157086603],"iteration":920,"passed_time":0.8221212724,"remaining_time":0.07051854562},
{"learn":[3.153354154],"iteration":921,"passed_time":0.8227452293,"remaining_time":0.06960317558},
{"learn":[3.153261317],"iteration":922,"passed_time":0.8233436972,"remaining_time":0.0686863106},
{"learn":[3.153168454],"iteration":923,"passed_time":0.8239488938,"remaining_time":0.06777068824},
{"learn":[3.152080399],"iteration":924,"passed_time":0.8245565985,"remaining_time":0.06685594042},
{"learn":[3.151635144],"iteration":925,"passed_time":0.8251672674,"remaining_time":0.06594209264},
{"learn":[3.147762655],"iteration":926,"passed_time":0.8257759089,"remaining_time":0.06502873932},
{"learn":[3.147172317],"iteration":927,"passed_time":0.8265182662,"remaining_time":0.06412641721},
{"learn":[3.146254125],"iteration":928,"passed_time":0.8272339826,"remaining_time":0.06322240341},
{"learn":[3.144869828],"iteration":929,"passed_time":0.8283743848,"remaining_time":0.06235076014},
{"learn":[3.143466218],"iteration":930,"passed_time":0.8291325853,"remaining_time":0.06145021309},
{"learn":[3.141919643],"iteration":931,"passed_time":0.8299395442,"remaining_time":0.06055352898},
{"learn":[3.141054135],"iteration":932,"passed_time":0.830575588,"remaining_time":0.05964476356},
{"learn":[3.139390417],"iteration":933,"passed_time":0.8311891074,"remaining_time":0.05873499046},
{"learn":[3.139025283],"iteration":934,"passed_time":0.8317977014,"remaining_time":0.05782550865},
{"learn":[3.137824183],"iteration":935,"passed_time":0.8323750113,"remaining_time":0.05691453069},
{"learn":[3.135620453],"iteration":936,"passed_time":0.8329893257,"remaining_time":0.05600675295},
{"learn":[3.13443178],"iteration":937,"passed_time":0.8336682441,"remaining_time":0.05510387114},
{"learn":[3.132765713],"iteration":938,"passed_time":0.8344414664,"remaining_time":0.0542075926},
{"learn":[3.131434124],"iteration":939,"passed_time":0.8350845326,"remaining_time":0.05330326804},
{"learn":[3.128384262],"iteration":940,"passed_time":0.8357177669,"remaining_time":0.0523988823},
{"learn":[3.128120455],"iteration":941,"passed_time":0.8362955294,"remaining_time":0.0514916568},
{"learn":[3.126314615],"iteration":942,"passed_time":0.8369409755,"remaining_time":0.05058922121},
{"learn":[3.125409666],"iteration":943,"passed_time":0.8375520522,"remaining_time":0.04968529123},
{"learn":[3.123072589],"iteration":944,"passed_time":0.8382333578,"remaining_time":0.04878606845},
{"learn":[3.122921099],"iteration":945,"passed_time":0.8388434208,"remaining_time":0.04788323967},
{"learn":[3.122182662],"iteration":946,"passed_time":0.839465115,"remaining_time":0.04698168014},
{"learn":[3.120040951],"iteration":947,"passed_time":0.8401062692,"remaining_time":0.04608177848},
{"learn":[3.118767799],"iteration":948,"passed_time":0.8407084582,"remaining_time":0.0451803281},
{"learn":[3.118203218],"iteration":949,"passed_time":0.8414416407,"remaining_time":0.04428640214},
{"learn":[3.116343362],"iteration":950,"passed_time":0.842069703,"remaining_time":0.04338739795},
{"learn":[3.11480829],"iteration":951,"passed_time":0.8427079769,"remaining_time":0.04248947783},
{"learn":[3.112607903],"iteration":952,"passed_time":0.8437742359,"remaining_time":0.04161320995},
{"learn":[3.111661241],"iteration":953,"passed_time":0.8446726639,"remaining_time":0.0407284513},
{"learn":[3.110249676],"iteration":954,"passed_time":0.8453747747,"remaining_time":0.03983441347},
{"learn":[3.107333579],"iteration":955,"passed_time":0.8460098267,"remaining_time":0.03893769077},
{"learn":[3.107149851],"iteration":956,"passed_time":0.8466504925,"remaining_time":0.03804176716},
{"learn":[3.106867336],"iteration":957,"passed_time":0.8473436121,"remaining_time":0.0371486761},
{"learn":[3.10364681],"iteration":958,"passed_time":0.8480488873,"remaining_time":0.03625652177},
{"learn":[3.102703811],"iteration":959,"passed_time":0.8486977265,"remaining_time":0.03536240527},
{"learn":[3.101469264],"iteration":960,"passed_time":0.8494082936,"remaining_time":0.03447130432},
{"learn":[3.09863569],"iteration":961,"passed_time":0.8502378911,"remaining_time":0.03358528052},
{"learn":[3.09645939],"iteration":962,"passed_time":0.8509128617,"remaining_time":0.0326934329},
{"learn":[3.096240186],"iteration":963,"passed_time":0.8515288061,"remaining_time":0.03179983093},
{"learn":[3.094838828],"iteration":964,"passed_time":0.8521122066,"remaining_time":0.03090562407},
{"learn":[3.094176802],"iteration":965,"passed_time":0.8527152927,"remaining_time":0.03001275357},
{"learn":[3.093182279],"iteration":966,"passed_time":0.8532900065,"remaining_time":0.02911951418},
{"learn":[3.090150687],"iteration":967,"passed_time":0.853855002,"remaining_time":0.02822661164},
{"learn":[3.088612829],"iteration":968,"passed_time":0.8544809455,"remaining_time":0.02733633572},
{"learn":[3.087153684],"iteration":969,"passed_time":0.8552239604,"remaining_time":0.02645022558},
{"learn":[3.085866843],"iteration":970,"passed_time":0.855880256,"remaining_time":0.02556182021},
{"learn":[3.082669094],"iteration":971,"passed_time":0.8565304067,"remaining_time":0.02467371542},
{"learn":[3.081047548],"iteration":972,"passed_time":0.8572222524,"remaining_time":0.02378725675},
{"learn":[3.079684322],"iteration":973,"passed_time":0.8578656434,"remaining_time":0.02289990424},
{"learn":[3.07613431],"iteration":974,"passed_time":0.8590642062,"remaining_time":0.02202728734},
{"learn":[3.074005935],"iteration":975,"passed_time":0.860226856,"remaining_time":0.02115311941},
{"learn":[3.072988853],"iteration":976,"passed_time":0.8611072207,"remaining_time":0.02027171553},
{"learn":[3.072344268],"iteration":977,"passed_time":0.8617677349,"remaining_time":0.01938536827},
{"learn":[3.070654438],"iteration":978,"passed_time":0.8624431125,"remaining_time":0.01849980119},
{"learn":[3.069724506],"iteration":979,"passed_time":0.8630768977,"remaining_time":0.01761381424},
{"learn":[3.067763166],"iteration":980,"passed_time":0.8636721858,"remaining_time":0.01672759585},
{"learn":[3.066737893],"iteration":981,"passed_time":0.8642599548,"remaining_time":0.01584183217},
{"learn":[3.065248174],"iteration":982,"passed_time":0.8648309789,"remaining_time":0.01495638519},
{"learn":[3.063186837],"iteration":983,"passed_time":0.8654124294,"remaining_time":0.01407174682},
{"learn":[3.062880371],"iteration":984,"passed_time":0.8660071012,"remaining_time":0.0131879254},
{"learn":[3.061288645],"iteration":985,"passed_time":0.8667010791,"remaining_time":0.01230610051},
{"learn":[3.059970575],"iteration":986,"passed_time":0.8673140161,"remaining_time":0.01142358887},
{"learn":[3.059576341],"iteration":987,"passed_time":0.8679495947,"remaining_time":0.01054189791},
{"learn":[3.058175919],"iteration":988,"passed_time":0.8685709621,"remaining_time":0.009660546595},
{"learn":[3.056830702],"iteration":989,"passed_time":0.8693080498,"remaining_time":0.008780889392},
{"learn":[3.056336579],"iteration":990,"passed_time":0.8700357811,"remaining_time":0.007901434945},
{"learn":[3.055810414],"iteration":991,"passed_time":0.8706843474,"remaining_time":0.007021647963},
{"learn":[3.055476518],"iteration":992,"passed_time":0.8712818317,"remaining_time":0.006141966588},
{"learn":[3.053331734],"iteration":993,"passed_time":0.8719264254,"remaining_time":0.005263137377},
{"learn":[3.050890374],"iteration":994,"passed_time":0.8725628758,"remaining_time":0.004384738069},
{"learn":[3.04972623],"iteration":995,"passed_time":0.8732192115,"remaining_time":0.003506904464},
{"learn":[3.047217327],"iteration":996,"passed_time":0.8742656786,"remaining_time":0.002630689103},
{"learn":[3.047155483],"iteration":997,"passed_time":0.8751527427,"remaining_time":0.001753813112},
{"learn":[3.04430671],"iteration":998,"passed_time":0.8761229842,"remaining_time":0.0008769999842},
{"learn":[3.042664195],"iteration":999,"passed_time":0.8769060029,"remaining_time":0}
]}